{"commit_hash": "0454c9bc4207b40f2712562fd2f21fe97d89b875", "env_name": "virtualenv-py3.13", "date": 1767817472000, "params": {"arch": "x86_64", "cpu": "AMD EPYC-Milan Processor", "machine": "adenzler-asv-runner", "num_cpu": "32", "os": "Linux 5.15.0-131-generic", "ram": "65836440", "python": "3.13"}, "python": "3.13", "requirements": {}, "env_vars": {}, "result_columns": ["result", "params", "version", "started_at", "duration", "stats_ci_99_a", "stats_ci_99_b", "stats_q_25", "stats_q_75", "stats_number", "stats_repeat", "samples", "profile"], "results": {"benchmark.AlohaCloth.track_metric": [null, [["'jit_duration'", "'solver_niter_mean'", "'solver_niter_p95'", "'device_memory_allocated'", "'step'", "'step.forward'", "'step.forward.fwd_position'", "'step.forward.fwd_position.kinematics'", "'step.forward.fwd_position.com_pos'", "'step.forward.fwd_position.camlight'", "'step.forward.fwd_position.crb'", "'step.forward.fwd_position.tendon_armature'", "'step.forward.fwd_position.collision'", "'step.forward.fwd_position.make_constraint'", "'step.forward.fwd_position.transmission'", "'step.forward.sensor_pos'", "'step.forward.fwd_velocity'", "'step.forward.fwd_velocity.com_vel'", "'step.forward.fwd_velocity.passive'", "'step.forward.fwd_velocity.rne'", "'step.forward.fwd_velocity.tendon_bias'", "'step.forward.sensor_vel'", "'step.forward.fwd_actuation'", "'step.forward.fwd_acceleration'", "'step.forward.fwd_acceleration.xfrc_accumulate'", "'step.forward.sensor_acc'", "'step.forward.solve'", "'step.euler'"]], "3c2a7a7a5a44816e680f74509cc8a620f4fd055126ce5d96cc6bb95c9cdef487", 1767852029517], "benchmark.AlohaPot.track_metric": [[92.71990402927622, 2.4958499755859376, 5.0, 471859200, 551.1459806002676, 543.9287146436982, 248.26445286453236, 36.44937892750022, 9.4470937465303, 1.9685117142671515, 11.191398445589584, 0.1744140628261448, 171.20500004239148, 14.535777350829449, 1.4172656258324423, 0.17276953178679832, 32.745226551924134, 9.334902324553696, 1.2037109322591277, 13.297199231601553, 0.1755507816909585, 0.17424218840744743, 1.5782968793018881, 7.878730466472916, 2.1307070285274676, 0.16903125002443176, 251.14112511801068, 6.702800772018236], [["'jit_duration'", "'solver_niter_mean'", "'solver_niter_p95'", "'device_memory_allocated'", "'step'", "'step.forward'", "'step.forward.fwd_position'", "'step.forward.fwd_position.kinematics'", "'step.forward.fwd_position.com_pos'", "'step.forward.fwd_position.camlight'", "'step.forward.fwd_position.crb'", "'step.forward.fwd_position.tendon_armature'", "'step.forward.fwd_position.collision'", "'step.forward.fwd_position.make_constraint'", "'step.forward.fwd_position.transmission'", "'step.forward.sensor_pos'", "'step.forward.fwd_velocity'", "'step.forward.fwd_velocity.com_vel'", "'step.forward.fwd_velocity.passive'", "'step.forward.fwd_velocity.rne'", "'step.forward.fwd_velocity.tendon_bias'", "'step.forward.sensor_vel'", "'step.forward.fwd_actuation'", "'step.forward.fwd_acceleration'", "'step.forward.fwd_acceleration.xfrc_accumulate'", "'step.forward.sensor_acc'", "'step.forward.solve'", "'step.euler'"]], "f1865afa96e71065b1d317f432d3ba032872121714a48c3729ab0bf8049592f3", 1767852130887, 38.099], "benchmark.AlohaSdf.track_metric": [null, [["'jit_duration'", "'solver_niter_mean'", "'solver_niter_p95'", "'device_memory_allocated'", "'step'", "'step.forward'", "'step.forward.fwd_position'", "'step.forward.fwd_position.kinematics'", "'step.forward.fwd_position.com_pos'", "'step.forward.fwd_position.camlight'", "'step.forward.fwd_position.crb'", "'step.forward.fwd_position.tendon_armature'", "'step.forward.fwd_position.collision'", "'step.forward.fwd_position.make_constraint'", "'step.forward.fwd_position.transmission'", "'step.forward.sensor_pos'", "'step.forward.fwd_velocity'", "'step.forward.fwd_velocity.com_vel'", "'step.forward.fwd_velocity.passive'", "'step.forward.fwd_velocity.rne'", "'step.forward.fwd_velocity.tendon_bias'", "'step.forward.sensor_vel'", "'step.forward.fwd_actuation'", "'step.forward.fwd_acceleration'", "'step.forward.fwd_acceleration.xfrc_accumulate'", "'step.forward.sensor_acc'", "'step.forward.solve'", "'step.euler'"]], "119ca919ec65f5ca833f00e50a476b9fadc23b5ee069931c162ea264b875c37c", 1767852171289], "benchmark.ApptronikApolloFlat.track_metric": [[55.66054631723091, 2.975197021484375, 5.0, 371195904, 540.9775037842337, 538.4889101842418, 107.84457011322957, 36.817488238739315, 10.142906236978888, 1.8448789044214209, 17.74430079240119, 0.17380859399906967, 7.440249996307102, 29.659636682481505, 2.1466484345182835, 2.0798515573687837, 42.85594910834334, 11.926304695407453, 1.2246874940728958, 18.148031222153804, 0.17337500011649354, 0.9385390598595222, 1.8760351536002418, 15.317484306251572, 3.064394532202641, 26.376558575066156, 339.1175781143829, 1.9744257805314192], [["'jit_duration'", "'solver_niter_mean'", "'solver_niter_p95'", "'device_memory_allocated'", "'step'", "'step.forward'", "'step.forward.fwd_position'", "'step.forward.fwd_position.kinematics'", "'step.forward.fwd_position.com_pos'", "'step.forward.fwd_position.camlight'", "'step.forward.fwd_position.crb'", "'step.forward.fwd_position.tendon_armature'", "'step.forward.fwd_position.collision'", "'step.forward.fwd_position.make_constraint'", "'step.forward.fwd_position.transmission'", "'step.forward.sensor_pos'", "'step.forward.fwd_velocity'", "'step.forward.fwd_velocity.com_vel'", "'step.forward.fwd_velocity.passive'", "'step.forward.fwd_velocity.rne'", "'step.forward.fwd_velocity.tendon_bias'", "'step.forward.sensor_vel'", "'step.forward.fwd_actuation'", "'step.forward.fwd_acceleration'", "'step.forward.fwd_acceleration.xfrc_accumulate'", "'step.forward.sensor_acc'", "'step.forward.solve'", "'step.euler'"]], "9be50ac165e18bd2b33bc453433bff32452a3074708f354c9438669adec01969", 1767852235250, 37.294], "benchmark.ApptronikApolloHfield.track_metric": [[73.02675461908802, 5.391747192382812, 8.0, 471859200, 928.0994068249129, 925.6048782845028, 346.8158710602438, 36.61037508936715, 10.128195302968379, 1.822800782633749, 17.832367188020726, 0.17350781293146156, 247.8599337482592, 27.779261728937854, 2.7258046884526266, 2.269882811788193, 43.3103086106712, 12.241246100529679, 1.2348867222726767, 18.267343744810205, 0.17314843809401737, 0.9657617196126012, 1.9086992282382198, 15.295339764634264, 3.007207037171611, 26.295066383681842, 486.7018589284271, 1.9729257830931601], [["'jit_duration'", "'solver_niter_mean'", "'solver_niter_p95'", "'device_memory_allocated'", "'step'", "'step.forward'", "'step.forward.fwd_position'", "'step.forward.fwd_position.kinematics'", "'step.forward.fwd_position.com_pos'", "'step.forward.fwd_position.camlight'", "'step.forward.fwd_position.crb'", "'step.forward.fwd_position.tendon_armature'", "'step.forward.fwd_position.collision'", "'step.forward.fwd_position.make_constraint'", "'step.forward.fwd_position.transmission'", "'step.forward.sensor_pos'", "'step.forward.fwd_velocity'", "'step.forward.fwd_velocity.com_vel'", "'step.forward.fwd_velocity.passive'", "'step.forward.fwd_velocity.rne'", "'step.forward.fwd_velocity.tendon_bias'", "'step.forward.sensor_vel'", "'step.forward.fwd_actuation'", "'step.forward.fwd_acceleration'", "'step.forward.fwd_acceleration.xfrc_accumulate'", "'step.forward.sensor_acc'", "'step.forward.solve'", "'step.euler'"]], "33efd5dbfcfd049253f0f0ab03a6a41d5f6058652ae6f8ec5a05dee79653e5bc", 1767852357385, 38.402], "benchmark.ApptronikApolloTerrain.track_metric": [[25.117334857117385, 2.974512451171875, 5.0, 2753560576, 1369.7810579324141, 1367.2459605149925, 885.4305978748016, 57.42655470385216, 10.474210934262373, 1.9374375062852778, 18.547796849816223, 0.1773085942176067, 756.0358713380992, 36.725125059092534, 2.205687498417319, 2.1502617175883643, 44.40118748971145, 12.60409766837256, 1.282292964788212, 18.567214809081634, 0.17697265688809694, 0.9582343758438583, 1.9480390675425951, 15.63863282717648, 3.1196562470086064, 26.850242198634078, 387.7544612623751, 2.01193359134777], [["'jit_duration'", "'solver_niter_mean'", "'solver_niter_p95'", "'device_memory_allocated'", "'step'", "'step.forward'", "'step.forward.fwd_position'", "'step.forward.fwd_position.kinematics'", "'step.forward.fwd_position.com_pos'", "'step.forward.fwd_position.camlight'", "'step.forward.fwd_position.crb'", "'step.forward.fwd_position.tendon_armature'", "'step.forward.fwd_position.collision'", "'step.forward.fwd_position.make_constraint'", "'step.forward.fwd_position.transmission'", "'step.forward.sensor_pos'", "'step.forward.fwd_velocity'", "'step.forward.fwd_velocity.com_vel'", "'step.forward.fwd_velocity.passive'", "'step.forward.fwd_velocity.rne'", "'step.forward.fwd_velocity.tendon_bias'", "'step.forward.sensor_vel'", "'step.forward.fwd_actuation'", "'step.forward.fwd_acceleration'", "'step.forward.fwd_acceleration.xfrc_accumulate'", "'step.forward.sensor_acc'", "'step.forward.solve'", "'step.euler'"]], "e9e1dc07190e5bbcc36b3caf70499e88f7d5566918813cb208c44e9743ac6a05", 1767852441208, 36.87], "benchmark.Cloth.track_metric": [null, [["'jit_duration'", "'solver_niter_mean'", "'solver_niter_p95'", "'device_memory_allocated'", "'step'", "'step.forward'", "'step.forward.fwd_position'", "'step.forward.fwd_position.kinematics'", "'step.forward.fwd_position.com_pos'", "'step.forward.fwd_position.camlight'", "'step.forward.fwd_position.crb'", "'step.forward.fwd_position.tendon_armature'", "'step.forward.fwd_position.collision'", "'step.forward.fwd_position.make_constraint'", "'step.forward.fwd_position.transmission'", "'step.forward.sensor_pos'", "'step.forward.fwd_velocity'", "'step.forward.fwd_velocity.com_vel'", "'step.forward.fwd_velocity.passive'", "'step.forward.fwd_velocity.rne'", "'step.forward.fwd_velocity.tendon_bias'", "'step.forward.sensor_vel'", "'step.forward.fwd_actuation'", "'step.forward.fwd_acceleration'", "'step.forward.fwd_acceleration.xfrc_accumulate'", "'step.forward.sensor_acc'", "'step.forward.solve'", "'step.euler'"]], "d4bba5d180fab88f55997ec4695f00e7871f3a53403fd2f8bd0f6a58d4cc734f", 1767852481598], "benchmark.FrankaEmikaPanda.track_metric": [[58.19328914396465, 1.106642852783203, 2.0, 337641472, 63.58580377855105, 59.292318368534325, 24.030996111832792, 13.08309474006819, 3.4914726570605126, 0.3180878902639961, 4.3530781294975895, 0.04331445319749605, 0.913045897846132, 0.9847216786056379, 0.37615820292558055, 0.043209961106072114, 13.83471093049593, 3.81943750062419, 0.331657230304927, 5.08226561896663, 0.04328417974974741, 0.043291992199101514, 0.48869335961398974, 2.450170899692239, 0.5319462888451199, 0.042187499992962785, 17.9074277075415, 4.163686518495524], [["'jit_duration'", "'solver_niter_mean'", "'solver_niter_p95'", "'device_memory_allocated'", "'step'", "'step.forward'", "'step.forward.fwd_position'", "'step.forward.fwd_position.kinematics'", "'step.forward.fwd_position.com_pos'", "'step.forward.fwd_position.camlight'", "'step.forward.fwd_position.crb'", "'step.forward.fwd_position.tendon_armature'", "'step.forward.fwd_position.collision'", "'step.forward.fwd_position.make_constraint'", "'step.forward.fwd_position.transmission'", "'step.forward.sensor_pos'", "'step.forward.fwd_velocity'", "'step.forward.fwd_velocity.com_vel'", "'step.forward.fwd_velocity.passive'", "'step.forward.fwd_velocity.rne'", "'step.forward.fwd_velocity.tendon_bias'", "'step.forward.sensor_vel'", "'step.forward.fwd_actuation'", "'step.forward.fwd_acceleration'", "'step.forward.fwd_acceleration.xfrc_accumulate'", "'step.forward.sensor_acc'", "'step.forward.solve'", "'step.implicit'"]], "78c420673eaf17d4d5cf73fc1804fba64306af796aad3daa70801546575585cb", 1767852545131, 38.047], "benchmark.Humanoid.track_metric": [[34.09903316292912, 1.4480953369140626, 3.0, 304087040, 379.5807068818249, 376.92607429926284, 94.27355069783516, 17.58622266970633, 6.265679681291658, 1.839003908230552, 14.188421871040191, 0.17588281255598304, 9.883328143587278, 40.24208206101321, 2.2127031240870565, 0.1720390629884605, 31.359515593067044, 8.073257807154732, 1.3119804650614242, 9.354773468658095, 0.1748242187034066, 0.17586718828965786, 2.048984369594109, 14.543488252456882, 1.6629179676783679, 0.1687382811326188, 232.31131614011247, 2.1447929680107336], [["'jit_duration'", "'solver_niter_mean'", "'solver_niter_p95'", "'device_memory_allocated'", "'step'", "'step.forward'", "'step.forward.fwd_position'", "'step.forward.fwd_position.kinematics'", "'step.forward.fwd_position.com_pos'", "'step.forward.fwd_position.camlight'", "'step.forward.fwd_position.crb'", "'step.forward.fwd_position.tendon_armature'", "'step.forward.fwd_position.collision'", "'step.forward.fwd_position.make_constraint'", "'step.forward.fwd_position.transmission'", "'step.forward.sensor_pos'", "'step.forward.fwd_velocity'", "'step.forward.fwd_velocity.com_vel'", "'step.forward.fwd_velocity.passive'", "'step.forward.fwd_velocity.rne'", "'step.forward.fwd_velocity.tendon_bias'", "'step.forward.sensor_vel'", "'step.forward.fwd_actuation'", "'step.forward.fwd_acceleration'", "'step.forward.fwd_acceleration.xfrc_accumulate'", "'step.forward.sensor_acc'", "'step.forward.solve'", "'step.euler'"]], "ed305730125f7377d0d0a900fdce7bedaf41d9ae7431ca110e2bf493b783e5dd", 1767852623884, 37.191], "benchmark.ThreeHumanoids.track_metric": [[68.99337102565914, 2.5999697265625, 4.0, 203423744, 5039.213128155097, 4860.536586958915, 539.1838127980009, 78.01556274353061, 29.974375038364087, 12.129875016398728, 39.275031278521055, 1.4000312510233925, 50.572843738336815, 303.80996875464916, 8.940906248426472, 1.38696875376354, 153.05840635846835, 44.25837503367802, 8.988437568405061, 51.8717187223956, 1.397875002339788, 1.3928437535923877, 14.16403122311749, 176.93381258868612, 14.035156206773536, 1.3551562503835157, 3958.114534500055, 174.54640586220194], [["'jit_duration'", "'solver_niter_mean'", "'solver_niter_p95'", "'device_memory_allocated'", "'step'", "'step.forward'", "'step.forward.fwd_position'", "'step.forward.fwd_position.kinematics'", "'step.forward.fwd_position.com_pos'", "'step.forward.fwd_position.camlight'", "'step.forward.fwd_position.crb'", "'step.forward.fwd_position.tendon_armature'", "'step.forward.fwd_position.collision'", "'step.forward.fwd_position.make_constraint'", "'step.forward.fwd_position.transmission'", "'step.forward.sensor_pos'", "'step.forward.fwd_velocity'", "'step.forward.fwd_velocity.com_vel'", "'step.forward.fwd_velocity.passive'", "'step.forward.fwd_velocity.rne'", "'step.forward.fwd_velocity.tendon_bias'", "'step.forward.sensor_vel'", "'step.forward.fwd_actuation'", "'step.forward.fwd_acceleration'", "'step.forward.fwd_acceleration.xfrc_accumulate'", "'step.forward.sensor_acc'", "'step.forward.solve'", "'step.euler'"]], "acfcbcedb670fb1f831d5c7a937123f167914f47c77121b66733dccc6d35dc3a", 1767852738664, 38.842]}, "durations": {"<setup_cache _src.benchmark:214>": 3.345019, "<setup_cache benchmark:125>": 101.370164, "<setup_cache benchmark:126>": 2.299234, "<setup_cache benchmark:127>": 63.96002, "<setup_cache benchmark:128>": 84.837933, "<setup_cache benchmark:129>": 45.418122, "<setup_cache benchmark:130>": 3.515813, "<setup_cache benchmark:131>": 63.532283, "<setup_cache benchmark:132>": 40.701387, "<setup_cache benchmark:133>": 77.585738}, "version": 2}