[{"name": "benchmark.AlohaCloth.track_metric", "idx": 0, "pretty_name": "benchmark.AlohaCloth.track_metric('jit_duration')", "last_rev": null, "last_value": null, "last_err": null, "prev_value": null, "change_rev": null}, {"name": "benchmark.AlohaCloth.track_metric", "idx": 1, "pretty_name": "benchmark.AlohaCloth.track_metric('solver_niter_mean')", "last_rev": null, "last_value": null, "last_err": null, "prev_value": null, "change_rev": null}, {"name": "benchmark.AlohaCloth.track_metric", "idx": 2, "pretty_name": "benchmark.AlohaCloth.track_metric('solver_niter_p95')", "last_rev": null, "last_value": null, "last_err": null, "prev_value": null, "change_rev": null}, {"name": "benchmark.AlohaCloth.track_metric", "idx": 3, "pretty_name": "benchmark.AlohaCloth.track_metric('device_memory_allocated')", "last_rev": null, "last_value": null, "last_err": null, "prev_value": null, "change_rev": null}, {"name": "benchmark.AlohaCloth.track_metric", "idx": 4, "pretty_name": "benchmark.AlohaCloth.track_metric('step')", "last_rev": null, "last_value": null, "last_err": null, "prev_value": null, "change_rev": null}, {"name": "benchmark.AlohaCloth.track_metric", "idx": 5, "pretty_name": "benchmark.AlohaCloth.track_metric('step.forward')", "last_rev": null, "last_value": null, "last_err": null, "prev_value": null, "change_rev": null}, {"name": "benchmark.AlohaCloth.track_metric", "idx": 6, "pretty_name": "benchmark.AlohaCloth.track_metric('step.forward.fwd_position')", "last_rev": null, "last_value": null, "last_err": null, "prev_value": null, "change_rev": null}, {"name": "benchmark.AlohaCloth.track_metric", "idx": 7, "pretty_name": "benchmark.AlohaCloth.track_metric('step.forward.fwd_position.kinematics')", "last_rev": null, "last_value": null, "last_err": null, "prev_value": null, "change_rev": null}, {"name": "benchmark.AlohaCloth.track_metric", "idx": 8, "pretty_name": "benchmark.AlohaCloth.track_metric('step.forward.fwd_position.com_pos')", "last_rev": null, "last_value": null, "last_err": null, "prev_value": null, "change_rev": null}, {"name": "benchmark.AlohaCloth.track_metric", "idx": 9, "pretty_name": "benchmark.AlohaCloth.track_metric('step.forward.fwd_position.camlight')", "last_rev": null, "last_value": null, "last_err": null, "prev_value": null, "change_rev": null}, {"name": "benchmark.AlohaCloth.track_metric", "idx": 10, "pretty_name": "benchmark.AlohaCloth.track_metric('step.forward.fwd_position.crb')", "last_rev": null, "last_value": null, "last_err": null, "prev_value": null, "change_rev": null}, {"name": "benchmark.AlohaCloth.track_metric", "idx": 11, "pretty_name": "benchmark.AlohaCloth.track_metric('step.forward.fwd_position.tendon_armature')", "last_rev": null, "last_value": null, "last_err": null, "prev_value": null, "change_rev": null}, {"name": "benchmark.AlohaCloth.track_metric", "idx": 12, "pretty_name": "benchmark.AlohaCloth.track_metric('step.forward.fwd_position.collision')", "last_rev": null, "last_value": null, "last_err": null, "prev_value": null, "change_rev": null}, {"name": "benchmark.AlohaCloth.track_metric", "idx": 13, "pretty_name": "benchmark.AlohaCloth.track_metric('step.forward.fwd_position.make_constraint')", "last_rev": null, "last_value": null, "last_err": null, "prev_value": null, "change_rev": null}, {"name": "benchmark.AlohaCloth.track_metric", "idx": 14, "pretty_name": "benchmark.AlohaCloth.track_metric('step.forward.fwd_position.transmission')", "last_rev": null, "last_value": null, "last_err": null, "prev_value": null, "change_rev": null}, {"name": "benchmark.AlohaCloth.track_metric", "idx": 15, "pretty_name": "benchmark.AlohaCloth.track_metric('step.forward.sensor_pos')", "last_rev": null, "last_value": null, "last_err": null, "prev_value": null, "change_rev": null}, {"name": "benchmark.AlohaCloth.track_metric", "idx": 16, "pretty_name": "benchmark.AlohaCloth.track_metric('step.forward.fwd_velocity')", "last_rev": null, "last_value": null, "last_err": null, "prev_value": null, "change_rev": null}, {"name": "benchmark.AlohaCloth.track_metric", "idx": 17, "pretty_name": "benchmark.AlohaCloth.track_metric('step.forward.fwd_velocity.com_vel')", "last_rev": null, "last_value": null, "last_err": null, "prev_value": null, "change_rev": null}, {"name": "benchmark.AlohaCloth.track_metric", "idx": 18, "pretty_name": "benchmark.AlohaCloth.track_metric('step.forward.fwd_velocity.passive')", "last_rev": null, "last_value": null, "last_err": null, "prev_value": null, "change_rev": null}, {"name": "benchmark.AlohaCloth.track_metric", "idx": 19, "pretty_name": "benchmark.AlohaCloth.track_metric('step.forward.fwd_velocity.rne')", "last_rev": null, "last_value": null, "last_err": null, "prev_value": null, "change_rev": null}, {"name": "benchmark.AlohaCloth.track_metric", "idx": 20, "pretty_name": "benchmark.AlohaCloth.track_metric('step.forward.fwd_velocity.tendon_bias')", "last_rev": null, "last_value": null, "last_err": null, "prev_value": null, "change_rev": null}, {"name": "benchmark.AlohaCloth.track_metric", "idx": 21, "pretty_name": "benchmark.AlohaCloth.track_metric('step.forward.sensor_vel')", "last_rev": null, "last_value": null, "last_err": null, "prev_value": null, "change_rev": null}, {"name": "benchmark.AlohaCloth.track_metric", "idx": 22, "pretty_name": "benchmark.AlohaCloth.track_metric('step.forward.fwd_actuation')", "last_rev": null, "last_value": null, "last_err": null, "prev_value": null, "change_rev": null}, {"name": "benchmark.AlohaCloth.track_metric", "idx": 23, "pretty_name": "benchmark.AlohaCloth.track_metric('step.forward.fwd_acceleration')", "last_rev": null, "last_value": null, "last_err": null, "prev_value": null, "change_rev": null}, {"name": "benchmark.AlohaCloth.track_metric", "idx": 24, "pretty_name": "benchmark.AlohaCloth.track_metric('step.forward.fwd_acceleration.xfrc_accumulate')", "last_rev": null, "last_value": null, "last_err": null, "prev_value": null, "change_rev": null}, {"name": "benchmark.AlohaCloth.track_metric", "idx": 25, "pretty_name": "benchmark.AlohaCloth.track_metric('step.forward.sensor_acc')", "last_rev": null, "last_value": null, "last_err": null, "prev_value": null, "change_rev": null}, {"name": "benchmark.AlohaCloth.track_metric", "idx": 26, "pretty_name": "benchmark.AlohaCloth.track_metric('step.forward.solve')", "last_rev": null, "last_value": null, "last_err": null, "prev_value": null, "change_rev": null}, {"name": "benchmark.AlohaCloth.track_metric", "idx": 27, "pretty_name": "benchmark.AlohaCloth.track_metric('step.euler')", "last_rev": null, "last_value": null, "last_err": null, "prev_value": null, "change_rev": null}, {"name": "benchmark.AlohaPot.track_metric", "idx": 0, "pretty_name": "benchmark.AlohaPot.track_metric('jit_duration')", "last_rev": 3880, "last_value": 84.05682568298653, "last_err": 5.209641802489781, "prev_value": null, "change_rev": null}, {"name": "benchmark.AlohaPot.track_metric", "idx": 1, "pretty_name": "benchmark.AlohaPot.track_metric('solver_niter_mean')", "last_rev": 3880, "last_value": 2.4971824951171877, "last_err": 0.0006686900745737987, "prev_value": 2.4930020751953124, "change_rev": [3618, 3663]}, {"name": "benchmark.AlohaPot.track_metric", "idx": 2, "pretty_name": "benchmark.AlohaPot.track_metric('solver_niter_p95')", "last_rev": 3880, "last_value": 5.0, "last_err": 0.0, "prev_value": 8.0, "change_rev": [3039, 3074]}, {"name": "benchmark.AlohaPot.track_metric", "idx": 3, "pretty_name": "benchmark.AlohaPot.track_metric('device_memory_allocated')", "last_rev": 3880, "last_value": 471859200.0, "last_err": 0.0, "prev_value": 505413632.0, "change_rev": [3719, 3757]}, {"name": "benchmark.AlohaPot.track_metric", "idx": 4, "pretty_name": "benchmark.AlohaPot.track_metric('step')", "last_rev": 3880, "last_value": 565.8239318145206, "last_err": 5.4671586923567315, "prev_value": 756.321949098492, "change_rev": [3039, 3074]}, {"name": "benchmark.AlohaPot.track_metric", "idx": 5, "pretty_name": "benchmark.AlohaPot.track_metric('step.forward')", "last_rev": 3880, "last_value": 558.704873532406, "last_err": 5.48598719996378, "prev_value": 749.3212230328936, "change_rev": [3039, 3074]}, {"name": "benchmark.AlohaPot.track_metric", "idx": 6, "pretty_name": "benchmark.AlohaPot.track_metric('step.forward.fwd_position')", "last_rev": 3880, "last_value": 248.19384382863063, "last_err": 6.74976002977379, "prev_value": null, "change_rev": null}, {"name": "benchmark.AlohaPot.track_metric", "idx": 7, "pretty_name": "benchmark.AlohaPot.track_metric('step.forward.fwd_position.kinematics')", "last_rev": 3880, "last_value": 36.88282435541623, "last_err": 0.5097591259433308, "prev_value": null, "change_rev": null}, {"name": "benchmark.AlohaPot.track_metric", "idx": 8, "pretty_name": "benchmark.AlohaPot.track_metric('step.forward.fwd_position.com_pos')", "last_rev": 3880, "last_value": 9.574749694365892, "last_err": 0.2559714793673231, "prev_value": null, "change_rev": null}, {"name": "benchmark.AlohaPot.track_metric", "idx": 9, "pretty_name": "benchmark.AlohaPot.track_metric('step.forward.fwd_position.camlight')", "last_rev": 3880, "last_value": 2.017250000790227, "last_err": 0.02040794880863445, "prev_value": null, "change_rev": null}, {"name": "benchmark.AlohaPot.track_metric", "idx": 10, "pretty_name": "benchmark.AlohaPot.track_metric('step.forward.fwd_position.crb')", "last_rev": 3880, "last_value": 10.856875037461577, "last_err": 0.14483889244386447, "prev_value": null, "change_rev": null}, {"name": "benchmark.AlohaPot.track_metric", "idx": 11, "pretty_name": "benchmark.AlohaPot.track_metric('step.forward.fwd_position.tendon_armature')", "last_rev": 3880, "last_value": 0.17412499956037664, "last_err": 0.0014109670732248662, "prev_value": null, "change_rev": null}, {"name": "benchmark.AlohaPot.track_metric", "idx": 12, "pretty_name": "benchmark.AlohaPot.track_metric('step.forward.fwd_position.collision')", "last_rev": 3880, "last_value": 171.26008609920973, "last_err": 6.305847400310669, "prev_value": null, "change_rev": null}, {"name": "benchmark.AlohaPot.track_metric", "idx": 13, "pretty_name": "benchmark.AlohaPot.track_metric('step.forward.fwd_position.make_constraint')", "last_rev": 3880, "last_value": 14.399039073396125, "last_err": 0.1333243688967964, "prev_value": null, "change_rev": null}, {"name": "benchmark.AlohaPot.track_metric", "idx": 14, "pretty_name": "benchmark.AlohaPot.track_metric('step.forward.fwd_position.transmission')", "last_rev": 3880, "last_value": 1.3943203108510716, "last_err": 0.011428220821585455, "prev_value": 1.1788046982701417, "change_rev": [3091, 3103]}, {"name": "benchmark.AlohaPot.track_metric", "idx": 15, "pretty_name": "benchmark.AlohaPot.track_metric('step.forward.sensor_pos')", "last_rev": 3880, "last_value": 0.1734999995619546, "last_err": 0.0016047317268216058, "prev_value": null, "change_rev": null}, {"name": "benchmark.AlohaPot.track_metric", "idx": 16, "pretty_name": "benchmark.AlohaPot.track_metric('step.forward.fwd_velocity')", "last_rev": 3880, "last_value": 32.80094540605205, "last_err": 0.0764148140695157, "prev_value": null, "change_rev": null}, {"name": "benchmark.AlohaPot.track_metric", "idx": 17, "pretty_name": "benchmark.AlohaPot.track_metric('step.forward.fwd_velocity.com_vel')", "last_rev": 3880, "last_value": 9.464624917200126, "last_err": 0.0515229694943662, "prev_value": null, "change_rev": null}, {"name": "benchmark.AlohaPot.track_metric", "idx": 18, "pretty_name": "benchmark.AlohaPot.track_metric('step.forward.fwd_velocity.passive')", "last_rev": 3880, "last_value": 1.204624994443293, "last_err": 0.01016966039403413, "prev_value": null, "change_rev": null}, {"name": "benchmark.AlohaPot.track_metric", "idx": 19, "pretty_name": "benchmark.AlohaPot.track_metric('step.forward.fwd_velocity.rne')", "last_rev": 3880, "last_value": 13.223609361375566, "last_err": 0.0552022671434075, "prev_value": null, "change_rev": null}, {"name": "benchmark.AlohaPot.track_metric", "idx": 20, "pretty_name": "benchmark.AlohaPot.track_metric('step.forward.fwd_velocity.tendon_bias')", "last_rev": 3880, "last_value": 0.17412499956037664, "last_err": 0.0013495726198295055, "prev_value": null, "change_rev": null}, {"name": "benchmark.AlohaPot.track_metric", "idx": 21, "pretty_name": "benchmark.AlohaPot.track_metric('step.forward.sensor_vel')", "last_rev": 3880, "last_value": 0.1739726567109301, "last_err": 0.0018040979494382966, "prev_value": null, "change_rev": null}, {"name": "benchmark.AlohaPot.track_metric", "idx": 22, "pretty_name": "benchmark.AlohaPot.track_metric('step.forward.fwd_actuation')", "last_rev": 3880, "last_value": 1.5471250261498426, "last_err": 0.0254360837850913, "prev_value": null, "change_rev": null}, {"name": "benchmark.AlohaPot.track_metric", "idx": 23, "pretty_name": "benchmark.AlohaPot.track_metric('step.forward.fwd_acceleration')", "last_rev": 3880, "last_value": 8.264500069344649, "last_err": 0.24768401798833367, "prev_value": null, "change_rev": null}, {"name": "benchmark.AlohaPot.track_metric", "idx": 24, "pretty_name": "benchmark.AlohaPot.track_metric('step.forward.fwd_acceleration.xfrc_accumulate')", "last_rev": 3880, "last_value": 2.143648431683687, "last_err": 0.02321485137470964, "prev_value": null, "change_rev": null}, {"name": "benchmark.AlohaPot.track_metric", "idx": 25, "pretty_name": "benchmark.AlohaPot.track_metric('step.forward.sensor_acc')", "last_rev": 3880, "last_value": 0.16966796884787527, "last_err": 0.0014211379795558558, "prev_value": null, "change_rev": null}, {"name": "benchmark.AlohaPot.track_metric", "idx": 26, "pretty_name": "benchmark.AlohaPot.track_metric('step.forward.solve')", "last_rev": 3880, "last_value": 263.6244317909586, "last_err": 5.362137644018124, "prev_value": 430.79662517266115, "change_rev": [3039, 3074]}, {"name": "benchmark.AlohaPot.track_metric", "idx": 27, "pretty_name": "benchmark.AlohaPot.track_metric('step.euler')", "last_rev": 3880, "last_value": 6.708624997372681, "last_err": 0.014601465257631693, "prev_value": 6.5070624291365675, "change_rev": [3103, 3127]}, {"name": "benchmark.AlohaSdf.track_metric", "idx": 0, "pretty_name": "benchmark.AlohaSdf.track_metric('jit_duration')", "last_rev": 3349, "last_value": 76.13431276933989, "last_err": 6.14654055715849, "prev_value": null, "change_rev": null}, {"name": "benchmark.AlohaSdf.track_metric", "idx": 1, "pretty_name": "benchmark.AlohaSdf.track_metric('solver_niter_mean')", "last_rev": 3349, "last_value": 3.5031898193359376, "last_err": 0.0006028346011513738, "prev_value": 4.2548828125, "change_rev": [3039, 3074]}, {"name": "benchmark.AlohaSdf.track_metric", "idx": 2, "pretty_name": "benchmark.AlohaSdf.track_metric('solver_niter_p95')", "last_rev": 3349, "last_value": 5.0, "last_err": 0.0, "prev_value": 6.0, "change_rev": [3039, 3074]}, {"name": "benchmark.AlohaSdf.track_metric", "idx": 3, "pretty_name": "benchmark.AlohaSdf.track_metric('device_memory_allocated')", "last_rev": 3349, "last_value": 606076928.0, "last_err": 0.0, "prev_value": 639631360.0, "change_rev": [3246, 3267]}, {"name": "benchmark.AlohaSdf.track_metric", "idx": 4, "pretty_name": "benchmark.AlohaSdf.track_metric('step')", "last_rev": 3349, "last_value": 2323.998356005177, "last_err": 41.931357320496126, "prev_value": 3956.2370687781367, "change_rev": [3039, 3074]}, {"name": "benchmark.AlohaSdf.track_metric", "idx": 5, "pretty_name": "benchmark.AlohaSdf.track_metric('step.forward')", "last_rev": 3349, "last_value": 2317.229337291792, "last_err": 41.947474182387325, "prev_value": 3949.5900627807714, "change_rev": [3039, 3074]}, {"name": "benchmark.AlohaSdf.track_metric", "idx": 6, "pretty_name": "benchmark.AlohaSdf.track_metric('step.forward.fwd_position')", "last_rev": 3349, "last_value": 1537.6474225195125, "last_err": 41.35998660441194, "prev_value": 2969.040465337457, "change_rev": [3039, 3074]}, {"name": "benchmark.AlohaSdf.track_metric", "idx": 7, "pretty_name": "benchmark.AlohaSdf.track_metric('step.forward.fwd_position.kinematics')", "last_rev": 3349, "last_value": 25.107142439082963, "last_err": 0.01797461322894378, "prev_value": 25.561281255249924, "change_rev": [3229, 3246]}, {"name": "benchmark.AlohaSdf.track_metric", "idx": 8, "pretty_name": "benchmark.AlohaSdf.track_metric('step.forward.fwd_position.com_pos')", "last_rev": 3349, "last_value": 7.317562666912636, "last_err": 0.055578119884103216, "prev_value": 7.8697499357076595, "change_rev": [3103, 3127]}, {"name": "benchmark.AlohaSdf.track_metric", "idx": 9, "pretty_name": "benchmark.AlohaSdf.track_metric('step.forward.fwd_position.camlight')", "last_rev": 3349, "last_value": 2.03075000536046, "last_err": 0.004187501403407623, "prev_value": 2.0953125272171746, "change_rev": [3103, 3127]}, {"name": "benchmark.AlohaSdf.track_metric", "idx": 10, "pretty_name": "benchmark.AlohaSdf.track_metric('step.forward.fwd_position.crb')", "last_rev": 3349, "last_value": 9.659249658852787, "last_err": 0.04839580815314548, "prev_value": null, "change_rev": null}, {"name": "benchmark.AlohaSdf.track_metric", "idx": 11, "pretty_name": "benchmark.AlohaSdf.track_metric('step.forward.fwd_position.tendon_armature')", "last_rev": 3349, "last_value": 0.17399999956069223, "last_err": 0.002108333327062913, "prev_value": null, "change_rev": null}, {"name": "benchmark.AlohaSdf.track_metric", "idx": 12, "pretty_name": "benchmark.AlohaSdf.track_metric('step.forward.fwd_position.collision')", "last_rev": 3349, "last_value": 1456.797372782603, "last_err": 41.37944696336299, "prev_value": 2889.1466287605, "change_rev": [3039, 3074]}, {"name": "benchmark.AlohaSdf.track_metric", "idx": 13, "pretty_name": "benchmark.AlohaSdf.track_metric('step.forward.fwd_position.make_constraint')", "last_rev": 3349, "last_value": 33.67412504121603, "last_err": 0.05625000887769548, "prev_value": 30.098500005806272, "change_rev": [3091, 3103]}, {"name": "benchmark.AlohaSdf.track_metric", "idx": 14, "pretty_name": "benchmark.AlohaSdf.track_metric('step.forward.fwd_position.transmission')", "last_rev": 3349, "last_value": 1.2687343668744688, "last_err": 0.03459608898689718, "prev_value": null, "change_rev": null}, {"name": "benchmark.AlohaSdf.track_metric", "idx": 15, "pretty_name": "benchmark.AlohaSdf.track_metric('step.forward.sensor_pos')", "last_rev": 3349, "last_value": 0.1731249995629014, "last_err": 0.0014249999964022209, "prev_value": null, "change_rev": null}, {"name": "benchmark.AlohaSdf.track_metric", "idx": 16, "pretty_name": "benchmark.AlohaSdf.track_metric('step.forward.fwd_velocity')", "last_rev": 3349, "last_value": 30.990944913355634, "last_err": 0.05723376568009068, "prev_value": null, "change_rev": null}, {"name": "benchmark.AlohaSdf.track_metric", "idx": 17, "pretty_name": "benchmark.AlohaSdf.track_metric('step.forward.fwd_velocity.com_vel')", "last_rev": 3349, "last_value": 9.063937838618585, "last_err": 0.028229176192932453, "prev_value": null, "change_rev": null}, {"name": "benchmark.AlohaSdf.track_metric", "idx": 18, "pretty_name": "benchmark.AlohaSdf.track_metric('step.forward.fwd_velocity.passive')", "last_rev": 3349, "last_value": 1.2009999965130191, "last_err": 0.012291659750947778, "prev_value": null, "change_rev": null}, {"name": "benchmark.AlohaSdf.track_metric", "idx": 19, "pretty_name": "benchmark.AlohaSdf.track_metric('step.forward.fwd_velocity.rne')", "last_rev": 3349, "last_value": 11.86268787660083, "last_err": 0.0517666823422284, "prev_value": null, "change_rev": null}, {"name": "benchmark.AlohaSdf.track_metric", "idx": 20, "pretty_name": "benchmark.AlohaSdf.track_metric('step.forward.fwd_velocity.tendon_bias')", "last_rev": 3349, "last_value": 0.1735624995617968, "last_err": 0.0016541666620166022, "prev_value": null, "change_rev": null}, {"name": "benchmark.AlohaSdf.track_metric", "idx": 21, "pretty_name": "benchmark.AlohaSdf.track_metric('step.forward.sensor_vel')", "last_rev": 3349, "last_value": 0.17412499956037664, "last_err": 0.0019208333284836954, "prev_value": null, "change_rev": null}, {"name": "benchmark.AlohaSdf.track_metric", "idx": 22, "pretty_name": "benchmark.AlohaSdf.track_metric('step.forward.fwd_actuation')", "last_rev": 3349, "last_value": 1.5140625444587386, "last_err": 0.003445310952088221, "prev_value": 1.472562543483491, "change_rev": [3103, 3127]}, {"name": "benchmark.AlohaSdf.track_metric", "idx": 23, "pretty_name": "benchmark.AlohaSdf.track_metric('step.forward.fwd_acceleration')", "last_rev": 3349, "last_value": 7.017375101895595, "last_err": 0.029481458373733664, "prev_value": 6.399249892638181, "change_rev": [2917, 2927]}, {"name": "benchmark.AlohaSdf.track_metric", "idx": 24, "pretty_name": "benchmark.AlohaSdf.track_metric('step.forward.fwd_acceleration.xfrc_accumulate')", "last_rev": 3349, "last_value": 1.6692929654027466, "last_err": 0.010756383661221966, "prev_value": null, "change_rev": null}, {"name": "benchmark.AlohaSdf.track_metric", "idx": 25, "pretty_name": "benchmark.AlohaSdf.track_metric('step.forward.sensor_acc')", "last_rev": 3349, "last_value": 0.16931249957252703, "last_err": 0.0019416666617644296, "prev_value": null, "change_rev": null}, {"name": "benchmark.AlohaSdf.track_metric", "idx": 26, "pretty_name": "benchmark.AlohaSdf.track_metric('step.forward.solve')", "last_rev": 3349, "last_value": 737.4077500826388, "last_err": 0.41982949716673995, "prev_value": 740.0072501368413, "change_rev": [3185, 3206]}, {"name": "benchmark.AlohaSdf.track_metric", "idx": 27, "pretty_name": "benchmark.AlohaSdf.track_metric('step.euler')", "last_rev": 3349, "last_value": 6.254749843719765, "last_err": 0.016914068226014933, "prev_value": 6.092874943533388, "change_rev": [3103, 3127]}, {"name": "benchmark.ApptronikApolloFlat.track_metric", "idx": 0, "pretty_name": "benchmark.ApptronikApolloFlat.track_metric('jit_duration')", "last_rev": 3880, "last_value": 46.284719040384516, "last_err": 1.6916173809303847, "prev_value": 99.89261414099019, "change_rev": [3185, 3206]}, {"name": "benchmark.ApptronikApolloFlat.track_metric", "idx": 1, "pretty_name": "benchmark.ApptronikApolloFlat.track_metric('solver_niter_mean')", "last_rev": 3880, "last_value": 2.9752327880859375, "last_err": 0.0001905581825658119, "prev_value": 4.1666494140625, "change_rev": [3415, 3444]}, {"name": "benchmark.ApptronikApolloFlat.track_metric", "idx": 2, "pretty_name": "benchmark.ApptronikApolloFlat.track_metric('solver_niter_p95')", "last_rev": 3880, "last_value": 5.0, "last_err": 0.0, "prev_value": 7.0, "change_rev": [3415, 3444]}, {"name": "benchmark.ApptronikApolloFlat.track_metric", "idx": 3, "pretty_name": "benchmark.ApptronikApolloFlat.track_metric('device_memory_allocated')", "last_rev": 3880, "last_value": 371195904.0, "last_err": 0.0, "prev_value": 404750336.0, "change_rev": [3719, 3757]}, {"name": "benchmark.ApptronikApolloFlat.track_metric", "idx": 4, "pretty_name": "benchmark.ApptronikApolloFlat.track_metric('step')", "last_rev": 3880, "last_value": 569.6728129405528, "last_err": 13.75072003084872, "prev_value": 636.9352049368899, "change_rev": [3415, 3444]}, {"name": "benchmark.ApptronikApolloFlat.track_metric", "idx": 5, "pretty_name": "benchmark.ApptronikApolloFlat.track_metric('step.forward')", "last_rev": 3880, "last_value": 567.1849455393385, "last_err": 13.761094158613368, "prev_value": 634.4636170251761, "change_rev": [3415, 3444]}, {"name": "benchmark.ApptronikApolloFlat.track_metric", "idx": 6, "pretty_name": "benchmark.ApptronikApolloFlat.track_metric('step.forward.fwd_position')", "last_rev": 3880, "last_value": 107.71155076508876, "last_err": 0.33152795176168803, "prev_value": 102.46206058218377, "change_rev": [3415, 3444]}, {"name": "benchmark.ApptronikApolloFlat.track_metric", "idx": 7, "pretty_name": "benchmark.ApptronikApolloFlat.track_metric('step.forward.fwd_position.kinematics')", "last_rev": 3880, "last_value": 36.99241433059797, "last_err": 0.43014711579571496, "prev_value": null, "change_rev": null}, {"name": "benchmark.ApptronikApolloFlat.track_metric", "idx": 8, "pretty_name": "benchmark.ApptronikApolloFlat.track_metric('step.forward.fwd_position.com_pos')", "last_rev": 3880, "last_value": 10.162374802348495, "last_err": 0.01769416970394862, "prev_value": 10.979750078149664, "change_rev": [3103, 3127]}, {"name": "benchmark.ApptronikApolloFlat.track_metric", "idx": 9, "pretty_name": "benchmark.ApptronikApolloFlat.track_metric('step.forward.fwd_position.camlight')", "last_rev": 3880, "last_value": 1.850249969493234, "last_err": 0.023488941728142237, "prev_value": null, "change_rev": null}, {"name": "benchmark.ApptronikApolloFlat.track_metric", "idx": 10, "pretty_name": "benchmark.ApptronikApolloFlat.track_metric('step.forward.fwd_position.crb')", "last_rev": 3880, "last_value": 17.78175012259453, "last_err": 0.04863467369259091, "prev_value": 17.27362499877927, "change_rev": [3388, 3406]}, {"name": "benchmark.ApptronikApolloFlat.track_metric", "idx": 11, "pretty_name": "benchmark.ApptronikApolloFlat.track_metric('step.forward.fwd_position.tendon_armature')", "last_rev": 3880, "last_value": 0.17364843785117046, "last_err": 0.0013497936425935376, "prev_value": null, "change_rev": null}, {"name": "benchmark.ApptronikApolloFlat.track_metric", "idx": 12, "pretty_name": "benchmark.ApptronikApolloFlat.track_metric('step.forward.fwd_position.collision')", "last_rev": 3880, "last_value": 7.094749929365207, "last_err": 0.19967114058261975, "prev_value": null, "change_rev": null}, {"name": "benchmark.ApptronikApolloFlat.track_metric", "idx": 13, "pretty_name": "benchmark.ApptronikApolloFlat.track_metric('step.forward.fwd_position.make_constraint')", "last_rev": 3880, "last_value": 29.42510937464249, "last_err": 0.33213384956884273, "prev_value": 25.00087480984803, "change_rev": [3415, 3444]}, {"name": "benchmark.ApptronikApolloFlat.track_metric", "idx": 14, "pretty_name": "benchmark.ApptronikApolloFlat.track_metric('step.forward.fwd_position.transmission')", "last_rev": 3880, "last_value": 2.1483085914724143, "last_err": 0.0031124128049163525, "prev_value": 2.416718750396285, "change_rev": [3719, 3757]}, {"name": "benchmark.ApptronikApolloFlat.track_metric", "idx": 15, "pretty_name": "benchmark.ApptronikApolloFlat.track_metric('step.forward.sensor_pos')", "last_rev": 3880, "last_value": 2.0839570262296547, "last_err": 0.15009663294857195, "prev_value": null, "change_rev": null}, {"name": "benchmark.ApptronikApolloFlat.track_metric", "idx": 16, "pretty_name": "benchmark.ApptronikApolloFlat.track_metric('step.forward.fwd_velocity')", "last_rev": 3880, "last_value": 42.8985744183592, "last_err": 0.0488143615377408, "prev_value": null, "change_rev": null}, {"name": "benchmark.ApptronikApolloFlat.track_metric", "idx": 17, "pretty_name": "benchmark.ApptronikApolloFlat.track_metric('step.forward.fwd_velocity.com_vel')", "last_rev": 3880, "last_value": 11.94350027526525, "last_err": 0.033623548212212966, "prev_value": null, "change_rev": null}, {"name": "benchmark.ApptronikApolloFlat.track_metric", "idx": 18, "pretty_name": "benchmark.ApptronikApolloFlat.track_metric('step.forward.fwd_velocity.passive')", "last_rev": 3880, "last_value": 1.2317499804339604, "last_err": 0.00866487140949587, "prev_value": null, "change_rev": null}, {"name": "benchmark.ApptronikApolloFlat.track_metric", "idx": 19, "pretty_name": "benchmark.ApptronikApolloFlat.track_metric('step.forward.fwd_velocity.rne')", "last_rev": 3880, "last_value": 18.155289048081613, "last_err": 0.03390831810769291, "prev_value": null, "change_rev": null}, {"name": "benchmark.ApptronikApolloFlat.track_metric", "idx": 20, "pretty_name": "benchmark.ApptronikApolloFlat.track_metric('step.forward.fwd_velocity.tendon_bias')", "last_rev": 3880, "last_value": 0.1734999995619546, "last_err": 0.0015703862598731473, "prev_value": null, "change_rev": null}, {"name": "benchmark.ApptronikApolloFlat.track_metric", "idx": 21, "pretty_name": "benchmark.ApptronikApolloFlat.track_metric('step.forward.sensor_vel')", "last_rev": 3880, "last_value": 0.8915000101978876, "last_err": 0.022128240502452, "prev_value": null, "change_rev": null}, {"name": "benchmark.ApptronikApolloFlat.track_metric", "idx": 22, "pretty_name": "benchmark.ApptronikApolloFlat.track_metric('step.forward.fwd_actuation')", "last_rev": 3880, "last_value": 1.8831718763294703, "last_err": 0.012691033823171412, "prev_value": null, "change_rev": null}, {"name": "benchmark.ApptronikApolloFlat.track_metric", "idx": 23, "pretty_name": "benchmark.ApptronikApolloFlat.track_metric('step.forward.fwd_acceleration')", "last_rev": 3880, "last_value": 15.333464781178918, "last_err": 0.038204332321627246, "prev_value": 14.899874628099496, "change_rev": [3388, 3406]}, {"name": "benchmark.ApptronikApolloFlat.track_metric", "idx": 24, "pretty_name": "benchmark.ApptronikApolloFlat.track_metric('step.forward.fwd_acceleration.xfrc_accumulate')", "last_rev": 3880, "last_value": 3.0084335974152054, "last_err": 0.02018925462560322, "prev_value": null, "change_rev": null}, {"name": "benchmark.ApptronikApolloFlat.track_metric", "idx": 25, "pretty_name": "benchmark.ApptronikApolloFlat.track_metric('step.forward.sensor_acc')", "last_rev": 3880, "last_value": 26.187250250586658, "last_err": 0.1639779229148155, "prev_value": null, "change_rev": null}, {"name": "benchmark.ApptronikApolloFlat.track_metric", "idx": 26, "pretty_name": "benchmark.ApptronikApolloFlat.track_metric('step.forward.solve')", "last_rev": 3880, "last_value": 367.2547851165291, "last_err": 14.025090619964574, "prev_value": 440.86300005437806, "change_rev": [3415, 3444]}, {"name": "benchmark.ApptronikApolloFlat.track_metric", "idx": 27, "pretty_name": "benchmark.ApptronikApolloFlat.track_metric('step.euler')", "last_rev": 3880, "last_value": 1.9506249782352825, "last_err": 0.02056066645060505, "prev_value": null, "change_rev": null}, {"name": "benchmark.ApptronikApolloHfield.track_metric", "idx": 0, "pretty_name": "benchmark.ApptronikApolloHfield.track_metric('jit_duration')", "last_rev": 3880, "last_value": 60.840971189085394, "last_err": 17.40020285710396, "prev_value": null, "change_rev": null}, {"name": "benchmark.ApptronikApolloHfield.track_metric", "idx": 1, "pretty_name": "benchmark.ApptronikApolloHfield.track_metric('solver_niter_mean')", "last_rev": 3880, "last_value": 11.423376708984375, "last_err": 0.0, "prev_value": 11.8311728515625, "change_rev": [3866, 3880]}, {"name": "benchmark.ApptronikApolloHfield.track_metric", "idx": 2, "pretty_name": "benchmark.ApptronikApolloHfield.track_metric('solver_niter_p95')", "last_rev": 3880, "last_value": 100.0, "last_err": 0.0, "prev_value": 8.0, "change_rev": [3663, 3719]}, {"name": "benchmark.ApptronikApolloHfield.track_metric", "idx": 3, "pretty_name": "benchmark.ApptronikApolloHfield.track_metric('device_memory_allocated')", "last_rev": 3880, "last_value": 471859200.0, "last_err": 0.0, "prev_value": 538968064.0, "change_rev": [3719, 3757]}, {"name": "benchmark.ApptronikApolloHfield.track_metric", "idx": 4, "pretty_name": "benchmark.ApptronikApolloHfield.track_metric('step')", "last_rev": 3880, "last_value": 1934.7733242320828, "last_err": 32.96112301177345, "prev_value": 2695.680399541743, "change_rev": [3822, 3836]}, {"name": "benchmark.ApptronikApolloHfield.track_metric", "idx": 5, "pretty_name": "benchmark.ApptronikApolloHfield.track_metric('step.forward')", "last_rev": 3880, "last_value": 1900.7189784315415, "last_err": 37.63232125493232, "prev_value": 2647.2223932505585, "change_rev": [3822, 3836]}, {"name": "benchmark.ApptronikApolloHfield.track_metric", "idx": 6, "pretty_name": "benchmark.ApptronikApolloHfield.track_metric('step.forward.fwd_position')", "last_rev": 3880, "last_value": 254.9750039470382, "last_err": 34.058082889285565, "prev_value": null, "change_rev": null}, {"name": "benchmark.ApptronikApolloHfield.track_metric", "idx": 7, "pretty_name": "benchmark.ApptronikApolloHfield.track_metric('step.forward.fwd_position.kinematics')", "last_rev": 3880, "last_value": 36.96652369762887, "last_err": 0.4412703756830558, "prev_value": null, "change_rev": null}, {"name": "benchmark.ApptronikApolloHfield.track_metric", "idx": 8, "pretty_name": "benchmark.ApptronikApolloHfield.track_metric('step.forward.fwd_position.com_pos')", "last_rev": 3880, "last_value": 10.139624794646807, "last_err": 0.013057578843682468, "prev_value": 10.954437570489972, "change_rev": [3103, 3127]}, {"name": "benchmark.ApptronikApolloHfield.track_metric", "idx": 9, "pretty_name": "benchmark.ApptronikApolloHfield.track_metric('step.forward.fwd_position.camlight')", "last_rev": 3880, "last_value": 1.8192460946693245, "last_err": 0.01645717798441663, "prev_value": null, "change_rev": null}, {"name": "benchmark.ApptronikApolloHfield.track_metric", "idx": 10, "pretty_name": "benchmark.ApptronikApolloHfield.track_metric('step.forward.fwd_position.crb')", "last_rev": 3880, "last_value": 17.406374887286802, "last_err": 0.23849059773124712, "prev_value": null, "change_rev": null}, {"name": "benchmark.ApptronikApolloHfield.track_metric", "idx": 11, "pretty_name": "benchmark.ApptronikApolloHfield.track_metric('step.forward.fwd_position.tendon_armature')", "last_rev": 3880, "last_value": 0.17399999956069223, "last_err": 0.001064047766793971, "prev_value": null, "change_rev": null}, {"name": "benchmark.ApptronikApolloHfield.track_metric", "idx": 12, "pretty_name": "benchmark.ApptronikApolloHfield.track_metric('step.forward.fwd_position.collision')", "last_rev": 3880, "last_value": 154.97275002053357, "last_err": 34.66063841321711, "prev_value": null, "change_rev": null}, {"name": "benchmark.ApptronikApolloHfield.track_metric", "idx": 13, "pretty_name": "benchmark.ApptronikApolloHfield.track_metric('step.forward.fwd_position.make_constraint')", "last_rev": 3880, "last_value": 28.083000004698988, "last_err": 1.3086449610300577, "prev_value": null, "change_rev": null}, {"name": "benchmark.ApptronikApolloHfield.track_metric", "idx": 14, "pretty_name": "benchmark.ApptronikApolloHfield.track_metric('step.forward.fwd_position.transmission')", "last_rev": 3880, "last_value": 2.416373025766916, "last_err": 0.07210703700764043, "prev_value": 1.7482421902741407, "change_rev": [3091, 3103]}, {"name": "benchmark.ApptronikApolloHfield.track_metric", "idx": 15, "pretty_name": "benchmark.ApptronikApolloHfield.track_metric('step.forward.sensor_pos')", "last_rev": 3880, "last_value": 2.148800779082194, "last_err": 0.15646071779617657, "prev_value": null, "change_rev": null}, {"name": "benchmark.ApptronikApolloHfield.track_metric", "idx": 16, "pretty_name": "benchmark.ApptronikApolloHfield.track_metric('step.forward.fwd_velocity')", "last_rev": 3880, "last_value": 43.20760523478384, "last_err": 0.13541970213925694, "prev_value": null, "change_rev": null}, {"name": "benchmark.ApptronikApolloHfield.track_metric", "idx": 17, "pretty_name": "benchmark.ApptronikApolloHfield.track_metric('step.forward.fwd_velocity.com_vel')", "last_rev": 3880, "last_value": 12.215999699037638, "last_err": 0.09506254754908369, "prev_value": null, "change_rev": null}, {"name": "benchmark.ApptronikApolloHfield.track_metric", "idx": 18, "pretty_name": "benchmark.ApptronikApolloHfield.track_metric('step.forward.fwd_velocity.passive')", "last_rev": 3880, "last_value": 1.227624982220732, "last_err": 0.008262017299441723, "prev_value": null, "change_rev": null}, {"name": "benchmark.ApptronikApolloHfield.track_metric", "idx": 19, "pretty_name": "benchmark.ApptronikApolloHfield.track_metric('step.forward.fwd_velocity.rne')", "last_rev": 3880, "last_value": 18.211750293630757, "last_err": 0.042928968537554915, "prev_value": null, "change_rev": null}, {"name": "benchmark.ApptronikApolloHfield.track_metric", "idx": 20, "pretty_name": "benchmark.ApptronikApolloHfield.track_metric('step.forward.fwd_velocity.tendon_bias')", "last_rev": 3880, "last_value": 0.17412499956037664, "last_err": 0.0010815889867925126, "prev_value": null, "change_rev": null}, {"name": "benchmark.ApptronikApolloHfield.track_metric", "idx": 21, "pretty_name": "benchmark.ApptronikApolloHfield.track_metric('step.forward.sensor_vel')", "last_rev": 3880, "last_value": 0.9459570275680562, "last_err": 0.006988381011151199, "prev_value": 0.878511730320497, "change_rev": [3103, 3127]}, {"name": "benchmark.ApptronikApolloHfield.track_metric", "idx": 22, "pretty_name": "benchmark.ApptronikApolloHfield.track_metric('step.forward.fwd_actuation')", "last_rev": 3880, "last_value": 1.8934999596922353, "last_err": 0.006563014611133557, "prev_value": 1.7888125017861967, "change_rev": [3103, 3127]}, {"name": "benchmark.ApptronikApolloHfield.track_metric", "idx": 23, "pretty_name": "benchmark.ApptronikApolloHfield.track_metric('step.forward.fwd_acceleration')", "last_rev": 3880, "last_value": 15.263765644704108, "last_err": 0.04668678792811642, "prev_value": 14.978749614783737, "change_rev": [3388, 3406]}, {"name": "benchmark.ApptronikApolloHfield.track_metric", "idx": 24, "pretty_name": "benchmark.ApptronikApolloHfield.track_metric('step.forward.fwd_acceleration.xfrc_accumulate')", "last_rev": 3880, "last_value": 3.0554687757557986, "last_err": 0.02472684249763881, "prev_value": null, "change_rev": null}, {"name": "benchmark.ApptronikApolloHfield.track_metric", "idx": 25, "pretty_name": "benchmark.ApptronikApolloHfield.track_metric('step.forward.sensor_acc')", "last_rev": 3880, "last_value": 26.231125253616483, "last_err": 0.16336634933326902, "prev_value": null, "change_rev": null}, {"name": "benchmark.ApptronikApolloHfield.track_metric", "idx": 26, "pretty_name": "benchmark.ApptronikApolloHfield.track_metric('step.forward.solve')", "last_rev": 3880, "last_value": 1545.747418596875, "last_err": 36.251091718440875, "prev_value": 2205.1923710969277, "change_rev": [3822, 3836]}, {"name": "benchmark.ApptronikApolloHfield.track_metric", "idx": 27, "pretty_name": "benchmark.ApptronikApolloHfield.track_metric('step.euler')", "last_rev": 3880, "last_value": 33.51797266196854, "last_err": 0.10542970511551175, "prev_value": 15.077378919954754, "change_rev": [3851, 3866]}, {"name": "benchmark.ApptronikApolloTerrain.track_metric", "idx": 0, "pretty_name": "benchmark.ApptronikApolloTerrain.track_metric('jit_duration')", "last_rev": 3880, "last_value": 20.956114925444126, "last_err": 1.0236493409919443, "prev_value": 79.25083629717119, "change_rev": [3185, 3206]}, {"name": "benchmark.ApptronikApolloTerrain.track_metric", "idx": 1, "pretty_name": "benchmark.ApptronikApolloTerrain.track_metric('solver_niter_mean')", "last_rev": 3880, "last_value": 2.973998291015625, "last_err": 0.0002667658879206537, "prev_value": 3.63015234375, "change_rev": [3327, 3341]}, {"name": "benchmark.ApptronikApolloTerrain.track_metric", "idx": 2, "pretty_name": "benchmark.ApptronikApolloTerrain.track_metric('solver_niter_p95')", "last_rev": 3880, "last_value": 5.0, "last_err": 0.0, "prev_value": 6.0, "change_rev": [3327, 3341]}, {"name": "benchmark.ApptronikApolloTerrain.track_metric", "idx": 3, "pretty_name": "benchmark.ApptronikApolloTerrain.track_metric('device_memory_allocated')", "last_rev": 3880, "last_value": 2753560576.0, "last_err": 0.0, "prev_value": 2787115008.0, "change_rev": [3719, 3757]}, {"name": "benchmark.ApptronikApolloTerrain.track_metric", "idx": 4, "pretty_name": "benchmark.ApptronikApolloTerrain.track_metric('step')", "last_rev": 3880, "last_value": 1404.038176406175, "last_err": 53.4291393958243, "prev_value": null, "change_rev": null}, {"name": "benchmark.ApptronikApolloTerrain.track_metric", "idx": 5, "pretty_name": "benchmark.ApptronikApolloTerrain.track_metric('step.forward')", "last_rev": 3880, "last_value": 1401.5007097041234, "last_err": 53.45572543084481, "prev_value": null, "change_rev": null}, {"name": "benchmark.ApptronikApolloTerrain.track_metric", "idx": 6, "pretty_name": "benchmark.ApptronikApolloTerrain.track_metric('step.forward.fwd_position')", "last_rev": 3880, "last_value": 883.6598316556774, "last_err": 24.148417678485924, "prev_value": null, "change_rev": null}, {"name": "benchmark.ApptronikApolloTerrain.track_metric", "idx": 7, "pretty_name": "benchmark.ApptronikApolloTerrain.track_metric('step.forward.fwd_position.kinematics')", "last_rev": 3880, "last_value": 56.59321098573855, "last_err": 0.4432493339165024, "prev_value": 51.39978313854954, "change_rev": [3229, 3246]}, {"name": "benchmark.ApptronikApolloTerrain.track_metric", "idx": 8, "pretty_name": "benchmark.ApptronikApolloTerrain.track_metric('step.forward.fwd_position.com_pos')", "last_rev": 3880, "last_value": 10.271124839164258, "last_err": 0.0976513204780834, "prev_value": 11.149750136610237, "change_rev": [3103, 3127]}, {"name": "benchmark.ApptronikApolloTerrain.track_metric", "idx": 9, "pretty_name": "benchmark.ApptronikApolloTerrain.track_metric('step.forward.fwd_position.camlight')", "last_rev": 3880, "last_value": 1.8987499668128294, "last_err": 0.026189649515628226, "prev_value": null, "change_rev": null}, {"name": "benchmark.ApptronikApolloTerrain.track_metric", "idx": 10, "pretty_name": "benchmark.ApptronikApolloTerrain.track_metric('step.forward.fwd_position.crb')", "last_rev": 3880, "last_value": 17.84662515638047, "last_err": 0.26116197539453906, "prev_value": null, "change_rev": null}, {"name": "benchmark.ApptronikApolloTerrain.track_metric", "idx": 11, "pretty_name": "benchmark.ApptronikApolloTerrain.track_metric('step.forward.fwd_position.tendon_armature')", "last_rev": 3880, "last_value": 0.17503906319404905, "last_err": 0.0014379425252018508, "prev_value": null, "change_rev": null}, {"name": "benchmark.ApptronikApolloTerrain.track_metric", "idx": 12, "pretty_name": "benchmark.ApptronikApolloTerrain.track_metric('step.forward.fwd_position.collision')", "last_rev": 3880, "last_value": 755.111898703035, "last_err": 0.36211992846801877, "prev_value": 743.6257016088348, "change_rev": [3499, 3564]}, {"name": "benchmark.ApptronikApolloTerrain.track_metric", "idx": 13, "pretty_name": "benchmark.ApptronikApolloTerrain.track_metric('step.forward.fwd_position.make_constraint')", "last_rev": 3880, "last_value": 32.2284999765543, "last_err": 2.7968507631913044, "prev_value": null, "change_rev": null}, {"name": "benchmark.ApptronikApolloTerrain.track_metric", "idx": 14, "pretty_name": "benchmark.ApptronikApolloTerrain.track_metric('step.forward.fwd_position.transmission')", "last_rev": 3880, "last_value": 2.3179999893727654, "last_err": 0.07490047704550307, "prev_value": 1.6625117191324534, "change_rev": [3091, 3103]}, {"name": "benchmark.ApptronikApolloTerrain.track_metric", "idx": 15, "pretty_name": "benchmark.ApptronikApolloTerrain.track_metric('step.forward.sensor_pos')", "last_rev": 3880, "last_value": 2.1467499984737515, "last_err": 0.13002755939473815, "prev_value": null, "change_rev": null}, {"name": "benchmark.ApptronikApolloTerrain.track_metric", "idx": 16, "pretty_name": "benchmark.ApptronikApolloTerrain.track_metric('step.forward.fwd_velocity')", "last_rev": 3880, "last_value": 43.71788657226716, "last_err": 0.28935210571463993, "prev_value": null, "change_rev": null}, {"name": "benchmark.ApptronikApolloTerrain.track_metric", "idx": 17, "pretty_name": "benchmark.ApptronikApolloTerrain.track_metric('step.forward.fwd_velocity.com_vel')", "last_rev": 3880, "last_value": 12.427999695319158, "last_err": 0.11099027497553868, "prev_value": null, "change_rev": null}, {"name": "benchmark.ApptronikApolloTerrain.track_metric", "idx": 18, "pretty_name": "benchmark.ApptronikApolloTerrain.track_metric('step.forward.fwd_velocity.passive')", "last_rev": 3880, "last_value": 1.2417499769981077, "last_err": 0.016445979777275188, "prev_value": null, "change_rev": null}, {"name": "benchmark.ApptronikApolloTerrain.track_metric", "idx": 19, "pretty_name": "benchmark.ApptronikApolloTerrain.track_metric('step.forward.fwd_velocity.rne')", "last_rev": 3880, "last_value": 18.339000298510655, "last_err": 0.10184764107420188, "prev_value": null, "change_rev": null}, {"name": "benchmark.ApptronikApolloTerrain.track_metric", "idx": 20, "pretty_name": "benchmark.ApptronikApolloTerrain.track_metric('step.forward.fwd_velocity.tendon_bias')", "last_rev": 3880, "last_value": 0.17499999955816747, "last_err": 0.0015689124330934509, "prev_value": null, "change_rev": null}, {"name": "benchmark.ApptronikApolloTerrain.track_metric", "idx": 21, "pretty_name": "benchmark.ApptronikApolloTerrain.track_metric('step.forward.sensor_vel')", "last_rev": 3880, "last_value": 0.9152500074378622, "last_err": 0.022665091131879103, "prev_value": null, "change_rev": null}, {"name": "benchmark.ApptronikApolloTerrain.track_metric", "idx": 22, "pretty_name": "benchmark.ApptronikApolloTerrain.track_metric('step.forward.fwd_actuation')", "last_rev": 3880, "last_value": 1.9082499642308903, "last_err": 0.025912969412497915, "prev_value": null, "change_rev": null}, {"name": "benchmark.ApptronikApolloTerrain.track_metric", "idx": 23, "pretty_name": "benchmark.ApptronikApolloTerrain.track_metric('step.forward.fwd_acceleration')", "last_rev": 3880, "last_value": 15.613375013344921, "last_err": 0.07547874520241749, "prev_value": 14.948374717278057, "change_rev": [3388, 3406]}, {"name": "benchmark.ApptronikApolloTerrain.track_metric", "idx": 24, "pretty_name": "benchmark.ApptronikApolloTerrain.track_metric('step.forward.fwd_acceleration.xfrc_accumulate')", "last_rev": 3880, "last_value": 3.0520039204020577, "last_err": 0.02376966124688377, "prev_value": null, "change_rev": null}, {"name": "benchmark.ApptronikApolloTerrain.track_metric", "idx": 25, "pretty_name": "benchmark.ApptronikApolloTerrain.track_metric('step.forward.sensor_acc')", "last_rev": 3880, "last_value": 26.535250213783, "last_err": 0.21216621301065525, "prev_value": null, "change_rev": null}, {"name": "benchmark.ApptronikApolloTerrain.track_metric", "idx": 26, "pretty_name": "benchmark.ApptronikApolloTerrain.track_metric('step.forward.solve')", "last_rev": 3880, "last_value": 442.7281255775597, "last_err": 34.24264120848471, "prev_value": null, "change_rev": null}, {"name": "benchmark.ApptronikApolloTerrain.track_metric", "idx": 27, "pretty_name": "benchmark.ApptronikApolloTerrain.track_metric('step.euler')", "last_rev": 3880, "last_value": 1.984683588716507, "last_err": 0.029236152326086326, "prev_value": null, "change_rev": null}, {"name": "benchmark.Cloth.track_metric", "idx": 0, "pretty_name": "benchmark.Cloth.track_metric('jit_duration')", "last_rev": 3467, "last_value": 8.873668584506959, "last_err": 0.5787277729426327, "prev_value": null, "change_rev": null}, {"name": "benchmark.Cloth.track_metric", "idx": 1, "pretty_name": "benchmark.Cloth.track_metric('solver_niter_mean')", "last_rev": 3467, "last_value": 2.9745234375, "last_err": 0.0, "prev_value": 5.51491357421875, "change_rev": [3444, 3467]}, {"name": "benchmark.Cloth.track_metric", "idx": 2, "pretty_name": "benchmark.Cloth.track_metric('solver_niter_p95')", "last_rev": 3467, "last_value": 5.0, "last_err": 0.0, "prev_value": 11.0, "change_rev": [3444, 3467]}, {"name": "benchmark.Cloth.track_metric", "idx": 3, "pretty_name": "benchmark.Cloth.track_metric('device_memory_allocated')", "last_rev": 3467, "last_value": 17081303040.0, "last_err": 0.0, "prev_value": 9028239360.0, "change_rev": [3444, 3467]}, {"name": "benchmark.Cloth.track_metric", "idx": 4, "pretty_name": "benchmark.Cloth.track_metric('step')", "last_rev": 3467, "last_value": 62182.41994082928, "last_err": 0.0, "prev_value": 10524.333004839718, "change_rev": [3444, 3467]}, {"name": "benchmark.Cloth.track_metric", "idx": 5, "pretty_name": "benchmark.Cloth.track_metric('step.forward')", "last_rev": 3467, "last_value": 61875.63182786107, "last_err": 0.0, "prev_value": 10462.86424761638, "change_rev": [3444, 3467]}, {"name": "benchmark.Cloth.track_metric", "idx": 6, "pretty_name": "benchmark.Cloth.track_metric('step.forward.fwd_position')", "last_rev": 3467, "last_value": 16253.771986812353, "last_err": 0.0, "prev_value": 1482.488937675953, "change_rev": [3444, 3467]}, {"name": "benchmark.Cloth.track_metric", "idx": 7, "pretty_name": "benchmark.Cloth.track_metric('step.forward.fwd_position.kinematics')", "last_rev": 3467, "last_value": 722.3639975418337, "last_err": 0.0, "prev_value": 137.22387584857643, "change_rev": [3444, 3467]}, {"name": "benchmark.Cloth.track_metric", "idx": 8, "pretty_name": "benchmark.Cloth.track_metric('step.forward.fwd_position.com_pos')", "last_rev": 3467, "last_value": 360.99200579337776, "last_err": 0.0, "prev_value": 102.09499999473337, "change_rev": [3444, 3467]}, {"name": "benchmark.Cloth.track_metric", "idx": 9, "pretty_name": "benchmark.Cloth.track_metric('step.forward.fwd_position.camlight')", "last_rev": 3467, "last_value": 47.416001456440426, "last_err": 0.0, "prev_value": 6.3355000233968894, "change_rev": [3444, 3467]}, {"name": "benchmark.Cloth.track_metric", "idx": 10, "pretty_name": "benchmark.Cloth.track_metric('step.forward.fwd_position.crb')", "last_rev": 3467, "last_value": 194.17199988674838, "last_err": 0.0, "prev_value": 56.62300097901607, "change_rev": [3444, 3467]}, {"name": "benchmark.Cloth.track_metric", "idx": 11, "pretty_name": "benchmark.Cloth.track_metric('step.forward.fwd_position.tendon_armature')", "last_rev": 3467, "last_value": 5.5599999859623495, "last_err": 0.0, "prev_value": 0.6974999982389818, "change_rev": [3444, 3467]}, {"name": "benchmark.Cloth.track_metric", "idx": 12, "pretty_name": "benchmark.Cloth.track_metric('step.forward.fwd_position.collision')", "last_rev": 3467, "last_value": 906.8400018149987, "last_err": 0.0, "prev_value": 247.7360014891019, "change_rev": [3444, 3467]}, {"name": "benchmark.Cloth.track_metric", "idx": 13, "pretty_name": "benchmark.Cloth.track_metric('step.forward.fwd_position.make_constraint')", "last_rev": 3467, "last_value": 13961.536000482738, "last_err": 0.0, "prev_value": 920.6214999430813, "change_rev": [3444, 3467]}, {"name": "benchmark.Cloth.track_metric", "idx": 14, "pretty_name": "benchmark.Cloth.track_metric('step.forward.fwd_position.transmission')", "last_rev": 3467, "last_value": 5.5599999859623495, "last_err": 0.0, "prev_value": 0.6964999982415065, "change_rev": [3444, 3467]}, {"name": "benchmark.Cloth.track_metric", "idx": 15, "pretty_name": "benchmark.Cloth.track_metric('step.forward.sensor_pos')", "last_rev": 3467, "last_value": 5.587999985891656, "last_err": 0.0, "prev_value": 0.698499998236457, "change_rev": [3444, 3467]}, {"name": "benchmark.Cloth.track_metric", "idx": 16, "pretty_name": "benchmark.Cloth.track_metric('step.forward.fwd_velocity')", "last_rev": 3467, "last_value": 2942.952004726976, "last_err": 0.0, "prev_value": 614.5910035120323, "change_rev": [3444, 3467]}, {"name": "benchmark.Cloth.track_metric", "idx": 17, "pretty_name": "benchmark.Cloth.track_metric('step.forward.fwd_velocity.com_vel')", "last_rev": 3467, "last_value": 369.66800870141014, "last_err": 0.0, "prev_value": 74.56750136771007, "change_rev": [3444, 3467]}, {"name": "benchmark.Cloth.track_metric", "idx": 18, "pretty_name": "benchmark.Cloth.track_metric('step.forward.fwd_velocity.passive')", "last_rev": 3467, "last_value": 1872.6480120094493, "last_err": 0.0, "prev_value": 397.6572497485904, "change_rev": [3444, 3467]}, {"name": "benchmark.Cloth.track_metric", "idx": 19, "pretty_name": "benchmark.Cloth.track_metric('step.forward.fwd_velocity.rne')", "last_rev": 3467, "last_value": 667.9480077582411, "last_err": 0.0, "prev_value": 138.36200212244876, "change_rev": [3444, 3467]}, {"name": "benchmark.Cloth.track_metric", "idx": 20, "pretty_name": "benchmark.Cloth.track_metric('step.forward.fwd_velocity.tendon_bias')", "last_rev": 3467, "last_value": 5.455999986224924, "last_err": 0.0, "prev_value": 0.6959999982427689, "change_rev": [3444, 3467]}, {"name": "benchmark.Cloth.track_metric", "idx": 21, "pretty_name": "benchmark.Cloth.track_metric('step.forward.sensor_vel')", "last_rev": 3467, "last_value": 5.535999986022944, "last_err": 0.0, "prev_value": 0.6969999982402442, "change_rev": [3444, 3467]}, {"name": "benchmark.Cloth.track_metric", "idx": 22, "pretty_name": "benchmark.Cloth.track_metric('step.forward.fwd_actuation')", "last_rev": 3467, "last_value": 15.943999966111733, "last_err": 0.0, "prev_value": 2.5104999438099185, "change_rev": [3444, 3467]}, {"name": "benchmark.Cloth.track_metric", "idx": 23, "pretty_name": "benchmark.Cloth.track_metric('step.forward.fwd_acceleration')", "last_rev": 3467, "last_value": 2018.0640008766204, "last_err": 0.0, "prev_value": 154.4414994714316, "change_rev": [3444, 3467]}, {"name": "benchmark.Cloth.track_metric", "idx": 24, "pretty_name": "benchmark.Cloth.track_metric('step.forward.fwd_acceleration.xfrc_accumulate')", "last_rev": 3467, "last_value": 1765.979997930117, "last_err": 0.0, "prev_value": 110.00559284730116, "change_rev": [3444, 3467]}, {"name": "benchmark.Cloth.track_metric", "idx": 25, "pretty_name": "benchmark.Cloth.track_metric('step.forward.sensor_acc')", "last_rev": 3467, "last_value": 5.455999986224924, "last_err": 0.0, "prev_value": 0.6794999982844274, "change_rev": [3444, 3467]}, {"name": "benchmark.Cloth.track_metric", "idx": 26, "pretty_name": "benchmark.Cloth.track_metric('step.forward.solve')", "last_rev": 3467, "last_value": 40572.88395706564, "last_err": 0.0, "prev_value": 8192.948495154269, "change_rev": [3444, 3467]}, {"name": "benchmark.Cloth.track_metric", "idx": 27, "pretty_name": "benchmark.Cloth.track_metric('step.euler')", "last_rev": 3467, "last_value": 290.3520109830424, "last_err": 0.0, "prev_value": 59.1610001938534, "change_rev": [3444, 3467]}, {"name": "benchmark.FrankaEmikaPanda.track_metric", "idx": 0, "pretty_name": "benchmark.FrankaEmikaPanda.track_metric('jit_duration')", "last_rev": 3880, "last_value": 36.23297815397382, "last_err": 6.702896447508019, "prev_value": null, "change_rev": null}, {"name": "benchmark.FrankaEmikaPanda.track_metric", "idx": 1, "pretty_name": "benchmark.FrankaEmikaPanda.track_metric('solver_niter_mean')", "last_rev": 3880, "last_value": 1.1066521911621094, "last_err": 0.0, "prev_value": 1.1065753479003906, "change_rev": [3780, 3807]}, {"name": "benchmark.FrankaEmikaPanda.track_metric", "idx": 2, "pretty_name": "benchmark.FrankaEmikaPanda.track_metric('solver_niter_p95')", "last_rev": 3880, "last_value": 2.0, "last_err": 0.0, "prev_value": null, "change_rev": null}, {"name": "benchmark.FrankaEmikaPanda.track_metric", "idx": 3, "pretty_name": "benchmark.FrankaEmikaPanda.track_metric('device_memory_allocated')", "last_rev": 3880, "last_value": 337641472.0, "last_err": 0.0, "prev_value": 371195904.0, "change_rev": [3719, 3757]}, {"name": "benchmark.FrankaEmikaPanda.track_metric", "idx": 4, "pretty_name": "benchmark.FrankaEmikaPanda.track_metric('step')", "last_rev": 3880, "last_value": 61.8070139826159, "last_err": 1.2392531322614062, "prev_value": null, "change_rev": null}, {"name": "benchmark.FrankaEmikaPanda.track_metric", "idx": 5, "pretty_name": "benchmark.FrankaEmikaPanda.track_metric('step.forward')", "last_rev": 3880, "last_value": 57.51647156284889, "last_err": 1.1479375553910427, "prev_value": null, "change_rev": null}, {"name": "benchmark.FrankaEmikaPanda.track_metric", "idx": 6, "pretty_name": "benchmark.FrankaEmikaPanda.track_metric('step.forward.fwd_position')", "last_rev": 3880, "last_value": 24.17734859227494, "last_err": 0.3307981381644736, "prev_value": null, "change_rev": null}, {"name": "benchmark.FrankaEmikaPanda.track_metric", "idx": 7, "pretty_name": "benchmark.FrankaEmikaPanda.track_metric('step.forward.fwd_position.kinematics')", "last_rev": 3880, "last_value": 13.608608350295981, "last_err": 0.22166102826304268, "prev_value": null, "change_rev": null}, {"name": "benchmark.FrankaEmikaPanda.track_metric", "idx": 8, "pretty_name": "benchmark.FrankaEmikaPanda.track_metric('step.forward.fwd_position.com_pos')", "last_rev": 3880, "last_value": 3.480679688436794, "last_err": 0.03632098711046311, "prev_value": 3.683343799934846, "change_rev": [3103, 3127]}, {"name": "benchmark.FrankaEmikaPanda.track_metric", "idx": 9, "pretty_name": "benchmark.FrankaEmikaPanda.track_metric('step.forward.fwd_position.camlight')", "last_rev": 3880, "last_value": 0.325468746552815, "last_err": 0.004577664346903852, "prev_value": null, "change_rev": null}, {"name": "benchmark.FrankaEmikaPanda.track_metric", "idx": 10, "pretty_name": "benchmark.FrankaEmikaPanda.track_metric('step.forward.fwd_position.crb')", "last_rev": 3880, "last_value": 4.341860351360083, "last_err": 0.011339611189344265, "prev_value": 4.016296805275488, "change_rev": [3388, 3406]}, {"name": "benchmark.FrankaEmikaPanda.track_metric", "idx": 11, "pretty_name": "benchmark.FrankaEmikaPanda.track_metric('step.forward.fwd_position.tendon_armature')", "last_rev": 3880, "last_value": 0.043437499890330855, "last_err": 0.000325950753448897, "prev_value": null, "change_rev": null}, {"name": "benchmark.FrankaEmikaPanda.track_metric", "idx": 12, "pretty_name": "benchmark.FrankaEmikaPanda.track_metric('step.forward.fwd_position.collision')", "last_rev": 3880, "last_value": 0.9213437502921806, "last_err": 0.015087034321426565, "prev_value": 0.9929843692475515, "change_rev": [3103, 3127]}, {"name": "benchmark.FrankaEmikaPanda.track_metric", "idx": 13, "pretty_name": "benchmark.FrankaEmikaPanda.track_metric('step.forward.fwd_position.make_constraint')", "last_rev": 3880, "last_value": 0.999468746272214, "last_err": 0.007988849445208088, "prev_value": 0.9061406452701704, "change_rev": [3029, 3039]}, {"name": "benchmark.FrankaEmikaPanda.track_metric", "idx": 14, "pretty_name": "benchmark.FrankaEmikaPanda.track_metric('step.forward.fwd_position.transmission')", "last_rev": 3880, "last_value": 0.375343761362501, "last_err": 0.014137325442703205, "prev_value": null, "change_rev": null}, {"name": "benchmark.FrankaEmikaPanda.track_metric", "idx": 15, "pretty_name": "benchmark.FrankaEmikaPanda.track_metric('step.forward.sensor_pos')", "last_rev": 3880, "last_value": 0.043218749890883146, "last_err": 0.0003580667793462968, "prev_value": null, "change_rev": null}, {"name": "benchmark.FrankaEmikaPanda.track_metric", "idx": 16, "pretty_name": "benchmark.FrankaEmikaPanda.track_metric('step.forward.fwd_velocity')", "last_rev": 3880, "last_value": 13.79843651830015, "last_err": 0.02001579419159515, "prev_value": null, "change_rev": null}, {"name": "benchmark.FrankaEmikaPanda.track_metric", "idx": 17, "pretty_name": "benchmark.FrankaEmikaPanda.track_metric('step.forward.fwd_velocity.com_vel')", "last_rev": 3880, "last_value": 3.783517581268825, "last_err": 0.01896680466313039, "prev_value": null, "change_rev": null}, {"name": "benchmark.FrankaEmikaPanda.track_metric", "idx": 18, "pretty_name": "benchmark.FrankaEmikaPanda.track_metric('step.forward.fwd_velocity.passive')", "last_rev": 3880, "last_value": 0.33156249855892383, "last_err": 0.0013481081304269958, "prev_value": 0.31534374325303816, "change_rev": [3103, 3127]}, {"name": "benchmark.FrankaEmikaPanda.track_metric", "idx": 19, "pretty_name": "benchmark.FrankaEmikaPanda.track_metric('step.forward.fwd_velocity.rne')", "last_rev": 3880, "last_value": 5.075843774193345, "last_err": 0.012516512444288412, "prev_value": null, "change_rev": null}, {"name": "benchmark.FrankaEmikaPanda.track_metric", "idx": 20, "pretty_name": "benchmark.FrankaEmikaPanda.track_metric('step.forward.fwd_velocity.tendon_bias')", "last_rev": 3880, "last_value": 0.043437499890330855, "last_err": 0.00041054320691022493, "prev_value": null, "change_rev": null}, {"name": "benchmark.FrankaEmikaPanda.track_metric", "idx": 21, "pretty_name": "benchmark.FrankaEmikaPanda.track_metric('step.forward.sensor_vel')", "last_rev": 3880, "last_value": 0.043406249890409754, "last_err": 0.0004030070870897979, "prev_value": null, "change_rev": null}, {"name": "benchmark.FrankaEmikaPanda.track_metric", "idx": 22, "pretty_name": "benchmark.FrankaEmikaPanda.track_metric('step.forward.fwd_actuation')", "last_rev": 3880, "last_value": 0.48806542946522313, "last_err": 0.007171765682354782, "prev_value": null, "change_rev": null}, {"name": "benchmark.FrankaEmikaPanda.track_metric", "idx": 23, "pretty_name": "benchmark.FrankaEmikaPanda.track_metric('step.forward.fwd_acceleration')", "last_rev": 3880, "last_value": 2.4494999197486322, "last_err": 0.022965761908775643, "prev_value": null, "change_rev": null}, {"name": "benchmark.FrankaEmikaPanda.track_metric", "idx": 24, "pretty_name": "benchmark.FrankaEmikaPanda.track_metric('step.forward.fwd_acceleration.xfrc_accumulate')", "last_rev": 3880, "last_value": 0.5323740220433137, "last_err": 0.0005289716366658265, "prev_value": 0.5868208020274324, "change_rev": [3719, 3757]}, {"name": "benchmark.FrankaEmikaPanda.track_metric", "idx": 25, "pretty_name": "benchmark.FrankaEmikaPanda.track_metric('step.forward.sensor_acc')", "last_rev": 3880, "last_value": 0.042333007808537104, "last_err": 0.00039637383455135694, "prev_value": null, "change_rev": null}, {"name": "benchmark.FrankaEmikaPanda.track_metric", "idx": 26, "pretty_name": "benchmark.FrankaEmikaPanda.track_metric('step.forward.solve')", "last_rev": 3880, "last_value": 17.63476564337907, "last_err": 0.10249926223574828, "prev_value": 16.146749951076345, "change_rev": [3388, 3406]}, {"name": "benchmark.FrankaEmikaPanda.track_metric", "idx": 27, "pretty_name": "benchmark.FrankaEmikaPanda.track_metric('step.implicit')", "last_rev": 3880, "last_value": 4.1490634780529945, "last_err": 0.10427484102674155, "prev_value": null, "change_rev": null}, {"name": "benchmark.Humanoid.track_metric", "idx": 0, "pretty_name": "benchmark.Humanoid.track_metric('jit_duration')", "last_rev": 3880, "last_value": 30.075405063980725, "last_err": 4.913038655672247, "prev_value": null, "change_rev": null}, {"name": "benchmark.Humanoid.track_metric", "idx": 1, "pretty_name": "benchmark.Humanoid.track_metric('solver_niter_mean')", "last_rev": 3880, "last_value": 1.4482725830078125, "last_err": 7.74177102481556e-05, "prev_value": 1.4478998413085937, "change_rev": [3185, 3206]}, {"name": "benchmark.Humanoid.track_metric", "idx": 2, "pretty_name": "benchmark.Humanoid.track_metric('solver_niter_p95')", "last_rev": 3880, "last_value": 3.0, "last_err": 0.0, "prev_value": null, "change_rev": null}, {"name": "benchmark.Humanoid.track_metric", "idx": 3, "pretty_name": "benchmark.Humanoid.track_metric('device_memory_allocated')", "last_rev": 3880, "last_value": 304087040.0, "last_err": 0.0, "prev_value": 371195904.0, "change_rev": [3719, 3757]}, {"name": "benchmark.Humanoid.track_metric", "idx": 4, "pretty_name": "benchmark.Humanoid.track_metric('step')", "last_rev": 3880, "last_value": 387.3877076257486, "last_err": 3.380060461975792, "prev_value": null, "change_rev": null}, {"name": "benchmark.Humanoid.track_metric", "idx": 5, "pretty_name": "benchmark.Humanoid.track_metric('step.forward')", "last_rev": 3880, "last_value": 384.76531277410686, "last_err": 3.3662078277765826, "prev_value": null, "change_rev": null}, {"name": "benchmark.Humanoid.track_metric", "idx": 6, "pretty_name": "benchmark.Humanoid.track_metric('step.forward.fwd_position')", "last_rev": 3880, "last_value": 94.30024205357768, "last_err": 0.6084257942999994, "prev_value": null, "change_rev": null}, {"name": "benchmark.Humanoid.track_metric", "idx": 7, "pretty_name": "benchmark.Humanoid.track_metric('step.forward.fwd_position.kinematics')", "last_rev": 3880, "last_value": 18.101277564710472, "last_err": 0.33330862757827834, "prev_value": null, "change_rev": null}, {"name": "benchmark.Humanoid.track_metric", "idx": 8, "pretty_name": "benchmark.Humanoid.track_metric('step.forward.fwd_position.com_pos')", "last_rev": 3880, "last_value": 6.239074223231, "last_err": 0.0044023429129285635, "prev_value": 6.015562601987767, "change_rev": [3719, 3757]}, {"name": "benchmark.Humanoid.track_metric", "idx": 9, "pretty_name": "benchmark.Humanoid.track_metric('step.forward.fwd_position.camlight')", "last_rev": 3880, "last_value": 1.852906247449937, "last_err": 0.016941913149564225, "prev_value": null, "change_rev": null}, {"name": "benchmark.Humanoid.track_metric", "idx": 10, "pretty_name": "benchmark.Humanoid.track_metric('step.forward.fwd_position.crb')", "last_rev": 3880, "last_value": 14.082500219046779, "last_err": 0.07111639278487276, "prev_value": null, "change_rev": null}, {"name": "benchmark.Humanoid.track_metric", "idx": 11, "pretty_name": "benchmark.Humanoid.track_metric('step.forward.fwd_position.tendon_armature')", "last_rev": 3880, "last_value": 0.1734921878409068, "last_err": 0.001179392760023665, "prev_value": null, "change_rev": null}, {"name": "benchmark.Humanoid.track_metric", "idx": 12, "pretty_name": "benchmark.Humanoid.track_metric('step.forward.fwd_position.collision')", "last_rev": 3880, "last_value": 9.947249854121765, "last_err": 0.039096479012561546, "prev_value": 9.413749727173126, "change_rev": [3185, 3206]}, {"name": "benchmark.Humanoid.track_metric", "idx": 13, "pretty_name": "benchmark.Humanoid.track_metric('step.forward.fwd_position.make_constraint')", "last_rev": 3880, "last_value": 40.18487510711566, "last_err": 0.519261455235021, "prev_value": null, "change_rev": null}, {"name": "benchmark.Humanoid.track_metric", "idx": 14, "pretty_name": "benchmark.Humanoid.track_metric('step.forward.fwd_position.transmission')", "last_rev": 3880, "last_value": 2.284892589955234, "last_err": 0.04817284831233337, "prev_value": 1.6320937484124443, "change_rev": [3091, 3103]}, {"name": "benchmark.Humanoid.track_metric", "idx": 15, "pretty_name": "benchmark.Humanoid.track_metric('step.forward.sensor_pos')", "last_rev": 3880, "last_value": 0.1735976570813591, "last_err": 0.0013986586135645684, "prev_value": null, "change_rev": null}, {"name": "benchmark.Humanoid.track_metric", "idx": 16, "pretty_name": "benchmark.Humanoid.track_metric('step.forward.fwd_velocity')", "last_rev": 3880, "last_value": 31.381425553263398, "last_err": 0.060337123596702506, "prev_value": null, "change_rev": null}, {"name": "benchmark.Humanoid.track_metric", "idx": 17, "pretty_name": "benchmark.Humanoid.track_metric('step.forward.fwd_velocity.com_vel')", "last_rev": 3880, "last_value": 8.058988271841372, "last_err": 0.05416739453000943, "prev_value": null, "change_rev": null}, {"name": "benchmark.Humanoid.track_metric", "idx": 18, "pretty_name": "benchmark.Humanoid.track_metric('step.forward.fwd_velocity.passive')", "last_rev": 3880, "last_value": 1.3067578166783278, "last_err": 0.01772693710490613, "prev_value": null, "change_rev": null}, {"name": "benchmark.Humanoid.track_metric", "idx": 19, "pretty_name": "benchmark.Humanoid.track_metric('step.forward.fwd_velocity.rne')", "last_rev": 3880, "last_value": 9.355250365842949, "last_err": 0.02781912860642341, "prev_value": null, "change_rev": null}, {"name": "benchmark.Humanoid.track_metric", "idx": 20, "pretty_name": "benchmark.Humanoid.track_metric('step.forward.fwd_velocity.tendon_bias')", "last_rev": 3880, "last_value": 0.17344921882056497, "last_err": 0.0012927476868775179, "prev_value": null, "change_rev": null}, {"name": "benchmark.Humanoid.track_metric", "idx": 21, "pretty_name": "benchmark.Humanoid.track_metric('step.forward.sensor_vel')", "last_rev": 3880, "last_value": 0.1733749995622702, "last_err": 0.002573555386274131, "prev_value": null, "change_rev": null}, {"name": "benchmark.Humanoid.track_metric", "idx": 22, "pretty_name": "benchmark.Humanoid.track_metric('step.forward.fwd_actuation')", "last_rev": 3880, "last_value": 1.9999999949504854, "last_err": 0.039774846973674394, "prev_value": null, "change_rev": null}, {"name": "benchmark.Humanoid.track_metric", "idx": 23, "pretty_name": "benchmark.Humanoid.track_metric('step.forward.fwd_acceleration')", "last_rev": 3880, "last_value": 14.11036524359588, "last_err": 0.16718647619200055, "prev_value": 11.395242417165719, "change_rev": [2927, 2939]}, {"name": "benchmark.Humanoid.track_metric", "idx": 24, "pretty_name": "benchmark.Humanoid.track_metric('step.forward.fwd_acceleration.xfrc_accumulate')", "last_rev": 3880, "last_value": 1.6672851572820946, "last_err": 0.00973157598781534, "prev_value": null, "change_rev": null}, {"name": "benchmark.Humanoid.track_metric", "idx": 25, "pretty_name": "benchmark.Humanoid.track_metric('step.forward.sensor_acc')", "last_rev": 3880, "last_value": 0.1696249995859489, "last_err": 0.0014915241531246826, "prev_value": null, "change_rev": null}, {"name": "benchmark.Humanoid.track_metric", "idx": 26, "pretty_name": "benchmark.Humanoid.track_metric('step.forward.solve')", "last_rev": 3880, "last_value": 240.2663749817293, "last_err": 3.066066544632568, "prev_value": null, "change_rev": null}, {"name": "benchmark.Humanoid.track_metric", "idx": 27, "pretty_name": "benchmark.Humanoid.track_metric('step.euler')", "last_rev": 3880, "last_value": 2.138992184882227, "last_err": 0.023859377356444073, "prev_value": null, "change_rev": null}, {"name": "benchmark.ThreeHumanoids.track_metric", "idx": 0, "pretty_name": "benchmark.ThreeHumanoids.track_metric('jit_duration')", "last_rev": 3880, "last_value": 51.6689962008968, "last_err": 5.445571042813822, "prev_value": null, "change_rev": null}, {"name": "benchmark.ThreeHumanoids.track_metric", "idx": 1, "pretty_name": "benchmark.ThreeHumanoids.track_metric('solver_niter_mean')", "last_rev": 3880, "last_value": 2.5996557617187497, "last_err": 0.001231980096726204, "prev_value": 2.8527255859375, "change_rev": [3039, 3074]}, {"name": "benchmark.ThreeHumanoids.track_metric", "idx": 2, "pretty_name": "benchmark.ThreeHumanoids.track_metric('solver_niter_p95')", "last_rev": 3880, "last_value": 4.0, "last_err": 0.0, "prev_value": 5.0, "change_rev": [3039, 3074]}, {"name": "benchmark.ThreeHumanoids.track_metric", "idx": 3, "pretty_name": "benchmark.ThreeHumanoids.track_metric('device_memory_allocated')", "last_rev": 3880, "last_value": 203423744.0, "last_err": 0.0, "prev_value": 270532608.0, "change_rev": [3719, 3757]}, {"name": "benchmark.ThreeHumanoids.track_metric", "idx": 4, "pretty_name": "benchmark.ThreeHumanoids.track_metric('step')", "last_rev": 3880, "last_value": 5180.639530066401, "last_err": 6.338871811749414, "prev_value": 5639.49078368023, "change_rev": [3757, 3780]}, {"name": "benchmark.ThreeHumanoids.track_metric", "idx": 5, "pretty_name": "benchmark.ThreeHumanoids.track_metric('step.forward')", "last_rev": 3880, "last_value": 5002.511725993827, "last_err": 6.419211073080078, "prev_value": 5461.469279369339, "change_rev": [3757, 3780]}, {"name": "benchmark.ThreeHumanoids.track_metric", "idx": 6, "pretty_name": "benchmark.ThreeHumanoids.track_metric('step.forward.fwd_position')", "last_rev": 3880, "last_value": 541.9406881555915, "last_err": 4.17083024677715, "prev_value": null, "change_rev": null}, {"name": "benchmark.ThreeHumanoids.track_metric", "idx": 7, "pretty_name": "benchmark.ThreeHumanoids.track_metric('step.forward.fwd_position.kinematics')", "last_rev": 3880, "last_value": 77.91825004096609, "last_err": 0.1405139070508691, "prev_value": 85.26190599513939, "change_rev": [3719, 3757]}, {"name": "benchmark.ThreeHumanoids.track_metric", "idx": 8, "pretty_name": "benchmark.ThreeHumanoids.track_metric('step.forward.fwd_position.com_pos')", "last_rev": 3880, "last_value": 29.3440002042189, "last_err": 0.5995369364478942, "prev_value": null, "change_rev": null}, {"name": "benchmark.ThreeHumanoids.track_metric", "idx": 9, "pretty_name": "benchmark.ThreeHumanoids.track_metric('step.forward.fwd_position.camlight')", "last_rev": 3880, "last_value": 11.908000371477101, "last_err": 0.14549400092842263, "prev_value": null, "change_rev": null}, {"name": "benchmark.ThreeHumanoids.track_metric", "idx": 10, "pretty_name": "benchmark.ThreeHumanoids.track_metric('step.forward.fwd_position.crb')", "last_rev": 3880, "last_value": 39.10103139423882, "last_err": 0.2387355161086164, "prev_value": null, "change_rev": null}, {"name": "benchmark.ThreeHumanoids.track_metric", "idx": 11, "pretty_name": "benchmark.ThreeHumanoids.track_metric('step.forward.fwd_position.tendon_armature')", "last_rev": 3880, "last_value": 1.3879999964956369, "last_err": 0.010011792935657932, "prev_value": null, "change_rev": null}, {"name": "benchmark.ThreeHumanoids.track_metric", "idx": 12, "pretty_name": "benchmark.ThreeHumanoids.track_metric('step.forward.fwd_position.collision')", "last_rev": 3880, "last_value": 51.02699980852776, "last_err": 0.5052800779423088, "prev_value": null, "change_rev": null}, {"name": "benchmark.ThreeHumanoids.track_metric", "idx": 13, "pretty_name": "benchmark.ThreeHumanoids.track_metric('step.forward.fwd_position.make_constraint')", "last_rev": 3880, "last_value": 302.27956239832565, "last_err": 3.5376256064924783, "prev_value": null, "change_rev": null}, {"name": "benchmark.ThreeHumanoids.track_metric", "idx": 14, "pretty_name": "benchmark.ThreeHumanoids.track_metric('step.forward.fwd_position.transmission')", "last_rev": 3880, "last_value": 8.96600026771921, "last_err": 0.29240978039764876, "prev_value": null, "change_rev": null}, {"name": "benchmark.ThreeHumanoids.track_metric", "idx": 15, "pretty_name": "benchmark.ThreeHumanoids.track_metric('step.forward.sensor_pos')", "last_rev": 3880, "last_value": 1.383999996505736, "last_err": 0.013137971694839438, "prev_value": null, "change_rev": null}, {"name": "benchmark.ThreeHumanoids.track_metric", "idx": 16, "pretty_name": "benchmark.ThreeHumanoids.track_metric('step.forward.fwd_velocity')", "last_rev": 3880, "last_value": 153.28212289023213, "last_err": 1.1993936498601094, "prev_value": null, "change_rev": null}, {"name": "benchmark.ThreeHumanoids.track_metric", "idx": 17, "pretty_name": "benchmark.ThreeHumanoids.track_metric('step.forward.fwd_velocity.com_vel')", "last_rev": 3880, "last_value": 44.62400055490434, "last_err": 0.3617265291088085, "prev_value": null, "change_rev": null}, {"name": "benchmark.ThreeHumanoids.track_metric", "idx": 18, "pretty_name": "benchmark.ThreeHumanoids.track_metric('step.forward.fwd_velocity.passive')", "last_rev": 3880, "last_value": 8.970000290901226, "last_err": 0.11255598851761842, "prev_value": null, "change_rev": null}, {"name": "benchmark.ThreeHumanoids.track_metric", "idx": 19, "pretty_name": "benchmark.ThreeHumanoids.track_metric('step.forward.fwd_velocity.rne')", "last_rev": 3880, "last_value": 51.82046877598623, "last_err": 0.27457683485546064, "prev_value": null, "change_rev": null}, {"name": "benchmark.ThreeHumanoids.track_metric", "idx": 20, "pretty_name": "benchmark.ThreeHumanoids.track_metric('step.forward.fwd_velocity.tendon_bias')", "last_rev": 3880, "last_value": 1.389000002859575, "last_err": 0.010980542708050465, "prev_value": null, "change_rev": null}, {"name": "benchmark.ThreeHumanoids.track_metric", "idx": 21, "pretty_name": "benchmark.ThreeHumanoids.track_metric('step.forward.sensor_vel')", "last_rev": 3880, "last_value": 1.3889999964931121, "last_err": 0.012010613170117859, "prev_value": null, "change_rev": null}, {"name": "benchmark.ThreeHumanoids.track_metric", "idx": 22, "pretty_name": "benchmark.ThreeHumanoids.track_metric('step.forward.fwd_actuation')", "last_rev": 3880, "last_value": 13.9420001378312, "last_err": 0.22959962719159074, "prev_value": null, "change_rev": null}, {"name": "benchmark.ThreeHumanoids.track_metric", "idx": 23, "pretty_name": "benchmark.ThreeHumanoids.track_metric('step.forward.fwd_acceleration')", "last_rev": 3880, "last_value": 176.82937510835472, "last_err": 1.0358751463189826, "prev_value": null, "change_rev": null}, {"name": "benchmark.ThreeHumanoids.track_metric", "idx": 24, "pretty_name": "benchmark.ThreeHumanoids.track_metric('step.forward.fwd_acceleration.xfrc_accumulate')", "last_rev": 3880, "last_value": 14.054937524633715, "last_err": 0.12607074540079888, "prev_value": null, "change_rev": null}, {"name": "benchmark.ThreeHumanoids.track_metric", "idx": 25, "pretty_name": "benchmark.ThreeHumanoids.track_metric('step.forward.sensor_acc')", "last_rev": 3880, "last_value": 1.3579999965713796, "last_err": 0.012979362983266051, "prev_value": null, "change_rev": null}, {"name": "benchmark.ThreeHumanoids.track_metric", "idx": 26, "pretty_name": "benchmark.ThreeHumanoids.track_metric('step.forward.solve')", "last_rev": 3880, "last_value": 4102.145953918807, "last_err": 6.406070839148015, "prev_value": 4561.343256151304, "change_rev": [3757, 3780]}, {"name": "benchmark.ThreeHumanoids.track_metric", "idx": 27, "pretty_name": "benchmark.ThreeHumanoids.track_metric('step.euler')", "last_rev": 3880, "last_value": 174.23340621462557, "last_err": 0.26327510789522657, "prev_value": 172.12699947413057, "change_rev": [3349, 3371]}]